Workbook

Sheet RAW DATA
A1: Emiten | B1: Tahun | C1: Current Assets | D1: Fixed Assets (Non CA) | E1: Total Assets | F1: Current Liabilities | G1: Total Liabilities | H1: Total Equity | I1: Sales Revenue | J1: EBIT (Operating Profit) | K1: Taxation (Tax Expenses) | L1: Net Income (Profit For the Year) | M1: Depreciation (Depreciation Expense) | N1: Year Listed | O1: AGE
A2: APLN | B2: 2019 | I2: 3792475607000
B3: 2020 | C3: 11676576495000 | D3: 18714783461000 | E3: 30391359956000 | F3: 6158911981000 | G3: 19036134922000 | H3: 11355225034000 | I3: 4956324700000 | J3: 1254480460000 | K3: 214555110000 | L3: 180144690000 | M3: 188737037000 | N3: 2010 | O3: =B3-N3 -> 10
B4: 2021 | C4: 11958891761000 | D4: 17652219432000 | E4: 29611111193000 | F4: 7314345544000 | G4: 19071333513000 | H4: 10539777680000 | I4: 4256245345000 | J4: 554113280000 | K4: 183387410000 | L4: -485227632000 | M4: 285912302000 | N4: 2010 | O4: =B4-N4 -> 11
B5: 2022 | C5: 11303386748000 | D5: 17314394993000 | E5: 28617781741000 | F5: 5771555207000 | G5: 16148220661000 | H5: 12469561080000 | I5: 8663824988000 | J5: 3768403830000 | K5: 312823830000 | L5: 2268910393000 | M5: 251429916000 | N5: 2010 | O5: =B5-N5 -> 12
B6: 2023 | C6: 11110900726000 | D6: 17216650886000 | E6: 28327551612000 | F6: 8538370071000 | G6: 14876147126000 | H6: 13451404486000 | I6: 4676651899000 | J6: 943423270000 | K6: 200314247000 | L6: 1164518767000 | M6: 242599591000 | N6: 2010 | O6: =B6-N6 -> 13
B7: 2024 | C7: 10864722185000 | D7: 15254955241000 | E7: 26119677426000 | F7: 4465148646000 | G7: 12335995789000 | H7: 13783681637000 | I7: 5576757087000 | J7: 1405599949000 | K7: 202679417000 | L7: 770526340000 | M7: 207349317000 | N7: 2010 | O7: =B7-N7 -> 14
A8: ASRI | B8: 2019 | I8: 3475677175000
B9: 2020 | C9: 2156001152000 | D9: 19070813719000 | E9: 21226814871000 | F9: 3198161431000 | G9: 11840666961000 | H9: 9386147910000 | I9: 1413251960000 | J9: 172780330000 | K9: 113380980000 | L9: -1036617870000 | M9: 104947860000 | N9: 2007 | O9: =B9-N9 -> 13
B10: 2021 | C10: 3034403543000 | D10: 18899571171000 | E10: 21933974714000 | F10: 3633263428000 | G10: 12397883478000 | H10: 9536091236000 | I10: 2847323720000 | J10: 1109773040000 | K10: 87131850000 | L10: 142928790000 | M10: 62520700000 | N10: 2007 | O10: =B10-N10 -> 14
B11: 2022 | C11: 3636178310000 | D11: 18662746961000 | E11: 22298925271000 | F11: 3717703477000 | G11: 11656300706000 | H11: 10642624565000 | I11: 4493531260000 | J11: 2139736770000 | K11: 123536910000 | L11: 1098364940000 | M11: 61418598000 | N11: 2007 | O11: =B11-N11 -> 15
B12: 2023 | C12: 2905301328000 | D12: 19330935536000 | E12: 22236236864000 | F12: 3688162066000 | G12: 10965051102000 | H12: 11271185762000 | I12: 3956015546000 | J12: 1667193500000 | K12: 129534290000 | L12: 637639854000 | M12: 49482744000 | N12: 2007 | O12: =B12-N12 -> 16
B13: 2024 | C13: 2832227835000 | D13: 19186803598000 | E13: 22019031433000 | F13: 3704391625000 | G13: 10683291993000 | H13: 11335739440000 | I13: 3433337156000 | J13: 1239889270000 | K13: 105105660000 | L13: 65136557000 | M13: 53956088000 | N13: 2007 | O13: =B13-N13 -> 17
A14: BAPA | B14: 2019 | I14: 24233788566
B15: 2020 | C15: =107744636327-82118871642 -> 25625764685 | D15: 116681006344 | E15: 142306771029 | F15: 7445381494 | G15: 8098923359 | H15: 134207847670 | I15: 9518983284 | J15: -2416160000 | K15: 378130000 | L15: -3737826580 | M15: 490282306 | N15: 2008 | O15: =B15-N15 -> 12
B16: 2021 | C16: 24281768224 | D16: 115289230111 | E16: 139570998335 | F16: 6792627578 | G16: 7171085839 | H16: 132399912496 | I16: 6194779683 | J16: -1708580000 | K16: 284410000 | L16: -2052255452 | M16: 490840486 | N16: 2008 | O16: =B16-N16 -> 13
B17: 2022 | C17: 22845370858 | D17: 112588642630 | E17: 135434013488 | F17: 6382787788 | G17: 6589092293 | H17: 128844921195 | I17: 3716043983 | J17: -3389301025 | K17: 209046878 | L17: -3712072464 | M17: 391354364 | N17: 2008 | O17: =B17-N17 -> 14
B18: 2023 | C18: 23288555973 | D18: 111573770722 | E18: 134862326695 | F18: 8585199688 | G18: 9062277504 | H18: 125800049191 | I18: 8119901265 | J18: -2331594337 | K18: 335560000 | L18: -2857333912 | M18: 511334453 | N18: 2008 | O18: =B18-N18 -> 15
B19: 2024 | C19: 23781119616 | D19: 108899900112 | E19: 132681019728 | F19: 10764200911 | G19: 12058589498 | H19: 120622430230 | I19: 4066108299 | J19: -4171546149 | K19: 164610000 | L19: -4572611851 | M19: 475830398 | N19: 2008 | O19: =B19-N19 -> 16
A20: BCIP | B20: 2019 | I20: 131094399577
B21: 2020 | C21: 395767984972 | D21: 513496477691 | E21: 909264462663 | F21: 308300895925 | G21: 462672453925 | H21: 446592008738 | I21: 73155228143 | J21: -4159761783 | K21: 1617220000 | L21: 12990820000 | M21: 2322249697 | N21: 2009 | O21: =B21-N21 -> 11
B22: 2021 | C22: 347736855343 | D22: 539336210053 | E22: 887073065396 | F22: 101144035422 | G22: 440374923594 | H22: 446698141802 | I22: 60409520263 | J22: -2724931140 | K22: 3408850000 | L22: 124179366 | M22: 2917343445 | N22: 2009 | O22: =B22-N22 -> 12
B23: 2022 | C23: 366321332034 | D23: 517713181088 | E23: 884034513122 | F23: 81907072930 | G23: 420288826352 | H23: 463745686769 | I23: 93742996267 | J23: 12378007493 | K23: 4138710000 | L23: 17063851989 | M23: 2271376466 | N23: 2009 | O23: =B23-N23 -> 13
B24: 2023 | C24: 380086878947 | D24: 530545675686 | E24: 910632554632 | F24: 84501811522 | G24: 429633626606 | H24: 480998928026 | I24: 94302986070 | J24: 11321818102 | K24: 3855150000 | L24: 17290964462 | M24: 2161799094 | N24: 2009 | O24: =B24-N24 -> 14
B25: 2024 | C25: 358863132348 | D25: 556635875773 | E25: 915499008121 | F25: 102828240347 | G25: 421739606444 | H25: 493759401677 | I25: 100002191228 | J25: 8298864109 | K25: 4014790000 | L25: 15271683642 | M25: 2686557561 | N25: 2009 | O25: =B25-N25 -> 15
A26: BEST | B26: 2019 | I26: 950545546999
B27: 2020 | C27: 2722827270198 | D27: 3559352959534 | E27: 6282180229732 | F27: 258669858995 | G27: 1925523126081 | H27: 4356657103651 | I27: 242320700845 | J27: 22157030000 | K27: 5817220000 | L27: -115219635076 | M27: 15870787108 | N27: 2012 | O27: =B27-N27 -> 8
B28: 2021 | C28: 2512714351541 | D28: 3533498033871 | E28: 6046212385412 | F28: 432585170220 | G28: 1752315039995 | H28: 4293897345417 | I28: 229835755986 | J28: 29479890000 | K28: 6142760000 | L28: -71095023263 | M28: 14475488334 | N28: 2012 | O28: =B28-N28 -> 9
B29: 2022 | C29: 2587148796402 | D29: 3491320112624 | E29: 6078468909026 | F29: 279952124627 | G29: 1749964841755 | H29: 4328504067271 | I29: 542834010731 | J29: 217390750000 | K29: 13683940000 | L29: 33729572546 | M29: 13411716896 | N29: 2012 | O29: =B29-N29 -> 10
B30: 2023 | C30: 2429482806528 | D30: 3510621542592 | E30: 5940104349120 | F30: 242206129142 | G30: 1572306529495 | H30: 4367797819625 | I30: 544314875513 | J30: 226477640000 | K30: 13096340000 | L30: 39528179905 | M30: 13981686993 | N30: 2012 | O30: =B30-N30 -> 11
B31: 2024 | C31: 2285508367613 | D31: 3541700062485 | E31: 5827208430098 | F31: 230503232839 | G31: 1401047153697 | H31: 4426161276401 | I31: 457589770772 | J31: 172045640000 | K31: 13403550000 | L31: 58582277467 | M31: 14014116310 | N31: 2012 | O31: =B31-N31 -> 12
A32: BIPP | B32: 2019 | I32: 359062749459
B33: 2020 | C33: 987418770826 | D33: 1139106559488 | E33: 2126525330314 | F33: 378439919105 | G33: 919581439010 | H33: 1206943891304 | I33: 529839404669 | J33: 143700277536 | K33: 16884070000 | L33: 94063090000 | M33: 7111076320 | N33: 1995 | O33: =B33-N33 -> 25
B34: 2021 | C34: 715590607726 | D34: 1329692580492 | E34: 2045283188218 | F34: 418513498673 | G34: 942012364746 | H34: 1103270823472 | I34: 293991355499 | J34: 67416473305 | K34: 12086260000 | L34: 19556640000 | M34: 6846229884 | N34: 1995 | O34: =B34-N34 -> 26
B35: 2022 | C35: 573208654112 | D35: 1315127852645 | E35: 1888336506757 | F35: 247729876368 | G35: 806384409413 | H35: 1081952097344 | I35: 327320863485 | J35: 77290508572 | K35: 12812350000 | L35: 25273690000 | M35: 7988936242 | N35: 1995 | O35: =B35-N35 -> 27
B36: 2023 | C36: 509753644372 | D36: 1435570222861 | E36: 1945323867233 | F36: 257412101987 | G36: 891896202079 | H36: 1053427665154 | I36: 264064990351 | J36: 54739339966 | K36: 9463760000 | L36: -4472990784 | M36: 10509468325 | N36: 1995 | O36: =B36-N36 -> 28
B37: 2024 | C37: 415752030680 | D37: 1445259166357 | E37: 1861011197037 | F37: 228206979554 | G37: 837870148178 | H37: 1023141048859 | I37: 258557430709 | J37: 56178512167 | K37: 15698040000 | L37: -6450817152 | M37: 11198281375 | N37: 1995 | O37: =B37-N37 -> 29
A38: BKDP | B38: 2019 | I38: 35174135994
B39: 2020 | C39: 86926323534 | D39: 703913851987 | E39: 790840175521 | F39: 171661406293 | G39: 309509265589 | H39: 481330909932 | I39: 19558738651 | J39: -28936032740 | K39: 1248580000 | L39: -31050114021 | M39: 3058630965 | N39: 2007 | O39: =B39-N39 -> 13
B40: 2021 | C40: 82564049560 | D40: 691575548789 | E40: 774139598349 | F40: 108482187823 | G40: 327575792987 | H40: 446563805362 | I40: 23401842549 | J40: -28529682149 | K40: 2250300000 | L40: -36260265843 | M40: 1381646874 | N40: 2007 | O40: =B40-N40 -> 14
B41: 2022 | C41: 67137207858 | D41: 689362499004 | E41: 756499706863 | F41: 129540100587 | G41: 343253957213 | H41: 413245749649 | I41: 26035856958 | J41: -25835667911 | K41: 3234750000 | L41: -33007921041 | M41: 1088585745 | N41: 2007 | O41: =B41-N41 -> 15
B42: 2023 | C42: 59018547316 | D42: 699220052510 | E42: 758238599826 | F42: 158947123114 | G42: 376331162576 | H42: 381907437249 | I42: 31211356619 | J42: -29357729455 | K42: 2971820000 | L42: -34594542018 | M42: 1042750130 | N42: 2007 | O42: =B42-N42 -> 16
B43: 2024 | C43: 56104668087 | D43: 696140494329 | E43: 752245162416 | F43: 183388019245 | G43: 406482108034 | H43: 345763054382 | I43: 30520490000 | J43: -30550273161 | K43: 3111160000 | L43: -35914000850 | M43: 1015053508 | N43: 2007 | O43: =B43-N43 -> 17
A44: BKSL | B44: 2019 | I44: 951421027715
B45: 2020 | C45: 4588731043660 | D45: 13782498930161 | E45: 18371229973821 | F45: 3270161549357 | G45: 8121131006426 | H45: 10250098967395 | I45: 451847230000 | J45: 15025170000 | K45: 14286230000 | L45: -556301780000 | M45: 13359230656 | N45: 1997 | O45: =B45-N45 -> 23
B46: 2021 | C46: 4654627251261 | D46: 12000362086900 | E46: 16654989338161 | F46: 1642561395481 | G46: 6168939794466 | H46: 10486049543695 | I46: 910709348365 | J46: 378256500000 | K46: 68176080000 | L46: 229270350000 | M46: 11738934783 | N46: 1997 | O46: =B46-N46 -> 24
B47: 2022 | C47: 4481703360284 | D47: 12240056903523 | E47: 16721760263807 | F47: 2216435731961 | G47: 6398549423657 | H47: 10323210840150 | I47: 672300266688 | J47: 257986080000 | K47: 13976050000 | L47: -167082790000 | M47: 12643185166 | N47: 1997 | O47: =B47-N47 -> 25
B48: 2023 | C48: 3574283102477 | D48: 16312594780943 | E48: 19886877883420 | F48: 3060809249354 | G48: 4745794622926 | H48: 15141083260494 | I48: 1720160600872 | J48: 469602950000 | K48: 40059370000 | L48: 317829464554 | M48: 16398255917 | N48: 1997 | O48: =B48-N48 -> 26
B49: 2024 | C49: 3763083379410 | D49: 17425207125996 | E49: 21188290505406 | F49: 3984626865675 | G49: 6034270819491 | H49: 15154019685915 | I49: 744068396829 | J49: 36884590000 | K49: 17536690000 | L49: 13930180346 | M49: 17813232199 | N49: 1997 | O49: =B49-N49 -> 27
A50: BSDE | B50: 2019 | I50: 7084864038574
B51: 2020 | C51: 28364293488112 | D51: 32498633098638 | E51: 60862926586750 | F51: 11832682024655 | G51: 26391824110926 | H51: 34471102475824 | I51: 6180589086059 | J51: 1982267044153 | K51: 237822390000 | L51: 486257814158 | M51: 80057479432 | N51: 2008 | O51: =B51-N51 -> 12
B52: 2021 | C52: 28397757188620 | D52: 33071954977036 | E52: 61469712165656 | F52: 10967892740436 | G52: 25575995151814 | H52: 35893717013842 | I52: 7654802250986 | J52: 2392256860902 | K52: 245062320000 | L52: 1538840956173 | M52: 76663992052 | N52: 2008 | O52: =B52-N52 -> 13
B53: 2022 | C53: 29586676145282 | D53: 35412727335505 | E53: 64999403480787 | F53: 11332854264009 | G53: 26953967352972 | H53: 38045436127815 | I53: 10235479955727 | J53: 3705009673794 | K53: 339110020000 | L53: 2656885590302 | M53: 74378557009 | N53: 2008 | O53: =B53-N53 -> 14
B54: 2023 | C54: 29374818540867 | D54: 37452829945526 | E54: 66827648486393 | F54: 11897714398814 | G54: 25626062282715 | H54: 41201586203678 | I54: 11539141250155 | J54: 2910167966982 | K54: 398893450000 | L54: 2259456837723 | M54: 68779568996 | N54: 2008 | O54: =B54-N54 -> 15
B55: 2024 | C55: 30896491642352 | D55: 45126857244494 | E55: 76023348886846 | F55: 14333486036630 | G55: 28704020732842 | H55: 47319328154004 | I55: 13796572148837 | J55: 4468905803578 | K55: 433154280000 | L55: 4917670536213 | M55: 86269755996 | N55: 2008 | O55: =B55-N55 -> 16
A56: CTRA | B56: 2019 | I56: 7608237000000
B57: 2020 | C57: 20645596000000 | D57: 18609591000000 | E57: 39255187000000 | F57: 11609414000000 | G57: 21797659000000 | H57: 17457528000000 | I57: 8070737000000 | J57: 2648089000000 | K57: 288435000000 | L57: 1370686000000 | M57: 162624000000 | N57: 1994 | O57: =B57-N57 -> 26
B58: 2021 | C58: 21916840000000 | D58: 18751571000000 | E58: 40668411000000 | F58: 10963375000000 | G58: 21274214000000 | H58: 19394197000000 | I58: 9729651000000 | J58: 3367683000000 | K58: 308998000000 | L58: 2087716000000 | M58: 162888000000 | N58: 1994 | O58: =B58-N58 -> 27
B59: 2022 | C59: 23733907000000 | D59: 18298708000000 | E59: 42032615000000 | F59: 10809037000000 | G59: 21017685000000 | H59: 21014930000000 | I59: 9126799000000 | J59: 3062626000000 | K59: 306545000000 | L59: 2002076000000 | M59: 166649000000 | N59: 1994 | O59: =B59-N59 -> 28
B60: 2023 | C60: 25747833000000 | D60: 18367382000000 | E60: 44115215000000 | F60: 10625396000000 | G60: 21490499000000 | H60: 22624716000000 | I60: 9245032000000 | J60: 2951424000000 | K60: 306744000000 | L60: 1909025000000 | M60: 181091000000 | N60: 1994 | O60: =B60-N60 -> 29
B61: 2024 | C61: 26429775000000 | D61: 20592927000000 | E61: 47022702000000 | F61: 13308121000000 | G61: 22407372000000 | H61: 24615330000000 | I61: 11187565000000 | J61: 3447050000000 | K61: 377753000000 | L61: 2327968000000 | M61: 202014000000 | N61: 1994 | O61: =B61-N61 -> 30
A62: DART | B62: 2019 | I62: 461440807000
B63: 2020 | C63: 182368717000 | D63: 6473752265000 | E63: 6656120982000 | F63: 609340883000 | G63: 3742012201000 | H63: 2914108781000 | I63: 324131001000 | J63: -62711200000 | K63: 6151370000 | L63: -400173079000 | M63: 69466097000 | N63: 1990 | O63: =B63-N63 -> 30
B64: 2021 | C64: 188892861000 | D64: 6415141729000 | E64: 6604034590000 | F64: 1287069124000 | G64: 4100747128000 | H64: 2503287462000 | I64: 290570233000 | J64: -67145770000 | K64: 2482250000 | L64: -411222141000 | M64: 63306637000 | N64: 1990 | O64: =B64-N64 -> 31
B65: 2022 | C65: 142287400000 | D65: 6320392697000 | E65: 6462680097000 | F65: 995858912000 | G65: 4380333825000 | H65: 2082346272000 | I65: 330155372000 | J65: -40981017000 | K65: 15753100000 | L65: -421159213000 | M65: 59149463000 | N65: 1990 | O65: =B65-N65 -> 32
B66: 2023 | C66: 124122818000 | D66: 6192846818000 | E66: 6316969636000 | F66: 823597854000 | G66: 4578440529000 | H66: 1738529107000 | I66: 433200487000 | J66: 28520691000 | K66: 31741970000 | L66: -343797532000 | M66: 53737952000 | N66: 1990 | O66: =B66-N66 -> 33
B67: 2024 | C67: 131682599000 | D67: 6076998917000 | E67: 6208681516000 | F67: 1310521180000 | G67: 4766522099000 | H67: 1442159417000 | I67: 511558731000 | J67: 64336243000 | K67: 34380170000 | L67: -296801679000 | M67: 55270295000 | N67: 1990 | O67: =B67-N67 -> 34
A68: DILD | B68: 2019 | I68: 2736388551409
B69: 2020 | C69: 4517663051391 | D69: 11181935824947 | E69: 15699598876338 | F69: 4367599682705 | G69: 9632497842455 | H69: 6067101033883 | I69: 2891388396351 | J69: 778389793916 | K69: 51053710000 | L69: 68962241069 | M69: 34288440722 | N69: 1991 | O69: =B69-N69 -> 29
B70: 2021 | C70: 6668818368239 | D70: 9791186459388 | E70: 16460004827627 | F70: 6489247592873 | G70: 10412628100009 | H70: 6047376727618 | I70: 2628631841339 | J70: 667006883515 | K70: 81877370000 | L70: -29065195094 | M70: 34290741240 | N70: 1991 | O70: =B70-N70 -> 30
B71: 2022 | C71: 6459625889455 | D71: 9892222488551 | E71: 16351848378006 | F71: 6191313428086 | G71: 10136195422586 | H71: 6215652955420 | I71: 3148754966275 | J71: 969226314682 | K71: 67194310000 | L71: 191967902267 | M71: 29646824123 | N71: 1991 | O71: =B71-N71 -> 31
B72: 2023 | C72: 4734769827971 | D72: 9869138315221 | E72: 14603908143192 | F72: 4152716613776 | G72: 8064726715168 | H72: 6539181428024 | I72: 3906826399192 | J72: 1270469130996 | K72: 95867130000 | L72: 758028371346 | M72: 32479550122 | N72: 1991 | O72: =B72-N72 -> 32
B73: 2024 | C73: 3870567366297 | D73: 9832985714600 | E73: 13703553080897 | F73: 3583108192834 | G73: 6956640610515 | H73: 6746912470382 | I73: 2553285289717 | J73: 454231193690 | K73: 143234270000 | L73: 263851731055 | M73: 35930484629 | N73: 1991 | O73: =B73-N73 -> 33
A74: DUTI | B74: 2019 | I74: 2459812402375
B75: 2020 | C75: 6073854519139 | D75: 7679770219746 | E75: 13753624738885 | F75: 1900303058105 | G75: 3423402804653 | H75: 10330221934232 | I75: 1724797535246 | J75: 580717124644 | K75: 87393230000 | L75: 638427373273 | M75: 34913620416 | N75: 1994 | O75: =B75-N75 -> 26
B76: 2021 | C76: 7924474668931 | D76: 7384448778848 | E76: 15308923447779 | F76: 2425833181007 | G76: 4347434120813 | H76: 10961489326966 | I76: 2177783404033 | J76: 622712848130 | K76: 94041170000 | L76: 730113120884 | M76: 33410387111 | N76: 1994 | O76: =B76-N76 -> 27
B77: 2022 | C77: 8165460067447 | D77: 7420718026514 | E77: 15586178093961 | F77: 3354912498892 | G77: 4659937738573 | H77: 10926240355388 | I77: 3017085551871 | J77: 979498820790 | K77: 124077760000 | L77: 846697244502 | M77: 31481698545 | N77: 1994 | O77: =B77-N77 -> 28
B78: 2023 | C78: 7632827881245 | D78: 7498661115021 | E78: 15131488996266 | F78: 2827910894867 | G78: 3670601789706 | H78: 11460887206560 | I78: 3862424155689 | J78: 1192461178136 | K78: 164122010000 | L78: 1285261384857 | M78: 21292381730 | N78: 1994 | O78: =B78-N78 -> 29
B79: 2024 | C79: 6697226908253 | D79: 7665170312298 | E79: 14362397220551 | F79: 1713363508919 | G79: 2494632246246 | H79: 11867764974305 | I79: 4422682660248 | J79: 1358967544305 | K79: 155787970000 | L79: 1375531266335 | M79: 21766164487 | N79: 1994 | O79: =B79-N79 -> 30
A80: ELTY | B80: 2019 | I80: 977548000000
B81: 2020 | C81: 2702974000000 | D81: 9120462000000 | E81: 11823436000000 | F81: 2481549000000 | G81: 3387644000000 | H81: 8435792000000 | I81: 616211000000 | J81: -200618000000 | K81: 9264000000 | L81: -326358000000 | M81: 101424000000 | N81: 1995 | O81: =B81-N81 -> 25
B82: 2021 | C82: 2742719000000 | D82: 8938484000000 | E82: 11681203000000 | F82: 2666128000000 | G82: 3533568000000 | H82: 8147635000000 | I82: 784410000000 | J82: -116294000000 | K82: 16253000000 | L82: -273529000000 | M82: 100341000000 | N82: 1995 | O82: =B82-N82 -> 26
B83: 2022 | C83: 2667546000000 | D83: 7245913000000 | E83: 9913459000000 | F83: 2116886000000 | G83: 2671612000000 | H83: 7241847000000 | I83: 1027232000000 | J83: -17950000000 | K83: 14935000000 | L83: -789619000000 | M83: 94981000000 | N83: 1995 | O83: =B83-N83 -> 27
B84: 2023 | C84: 2431035000000 | D84: 6208018000000 | E84: 8639053000000 | F84: 2002507000000 | G84: 2507808000000 | H84: 6131245000000 | I84: 1273390000000 | J84: -183152000000 | K84: 21337000000 | L84: -1122557000000 | M84: 60834000000 | N84: 1995 | O84: =B84-N84 -> 28
B85: 2024 | C85: 1621212000000 | D85: 7120805000000 | E85: 8742017000000 | F85: 1818658000000 | G85: 2717802000000 | H85: 6024215000000 | I85: 1226740000000 | J85: 56045000000 | K85: 18696000000 | L85: -101948000000 | M85: 66496000000 | N85: 1995 | O85: =B85-N85 -> 29
A86: EMDE | B86: 2019 | I86: 165189625230
B87: 2020 | C87: 1851347307718 | D87: 602706965777 | E87: 2454054273495 | F87: 887763447554 | G87: 1905692754656 | H87: 548361518839 | I87: 85684403962 | J87: -33457540000 | K87: 5009960000 | L87: -56617681066 | M87: 2773875230 | N87: 2011 | O87: =B87-N87 -> 9
B88: 2021 | C88: 1488507549729 | D88: 2240131441051 | E88: 3728638990780 | F88: 1001239817402 | G88: 2033688077681 | H88: 1694950913099 | I88: 173510721755 | J88: 26562450000 | K88: 33687170000 | L88: 1034201610092 | M88: 2498827972 | N88: 2011 | O88: =B88-N88 -> 10
B89: 2022 | C89: 1502657683212 | D89: 2241094053846 | E89: 3743751737058 | F89: 1095251094706 | G89: 2117499934233 | H89: 1626251802825 | I89: 153441610795 | J89: 15445310000 | K89: 6739480000 | L89: -68275169424 | M89: 2357605504 | N89: 2011 | O89: =B89-N89 -> 11
B90: 2023 | C90: 1491061329243 | D90: 2028193913640 | E90: 3519255242883 | F90: 1108683871338 | G90: 2161295035484 | H90: 1357960207399 | I90: 154587592125 | J90: 12178510000 | K90: 1900330000 | L90: -271564578143 | M90: 1878290105 | N90: 2011 | O90: =B90-N90 -> 12
B91: 2024 | C91: 1618231801714 | D91: 2129536838484 | E91: 3747768640198 | F91: 847351668732 | G91: 1867842626729 | H91: 1879926013469 | I91: 1353932364676 | J91: 558699770000 | K91: 37283470000 | L91: 522711993667 | M91: 1816314794 | N91: 2011 | O91: =B91-N91 -> 13
A92: FMII | B92: 2019 | I92: 84249947508
B93: 2020 | C93: 267196924710 | D93: 603510528360 | E93: 870707453070 | F93: 81634525401 | G93: 245524649894 | H93: 625182803176 | I93: 51320798915 | J93: 16616477301 | K93: 1313019970 | L93: -1481751003 | M93: 96171044 | N93: 2000 | O93: =B93-N93 -> 20
B94: 2021 | C94: 248069247814 | D94: 620961426811 | E94: 869030674625 | F94: 193806868880 | G94: 233332307567 | H94: 635698367058 | I94: 52738265883 | J94: 26273611515 | K94: 1359419402 | L94: 8562317113 | M94: 125097711 | N94: 2000 | O94: =B94-N94 -> 21
B95: 2022 | C95: 194478486688 | D95: 558387356383 | E95: 752865843071 | F95: 68336742190 | G95: 100867958685 | H95: 651997884387 | I95: 52372680139 | J95: 22783606882 | K95: 1327680636 | L95: 17293843958 | M95: 74341763 | N95: 2000 | O95: =B95-N95 -> 22
B96: 2023 | C96: 184695899175 | D96: 597639511714 | E96: 782335410889 | F96: 89641904121 | G96: 113016805012 | H96: 669318605877 | I96: 42580151783 | J96: 18588544666 | K96: 1068128541 | L96: 17362764969 | M96: 232449628 | N96: 2000 | O96: =B96-N96 -> 23
B97: 2024 | C97: 177129927079 | D97: 600179808282 | E97: 777309735361 | F97: 84398200320 | G97: 97645102677 | H97: 679664632684 | I97: 35317779779 | J97: 11099468010 | K97: 651446679 | L97: 10364124122 | M97: 267860668 | N97: 2000 | O97: =B97-N97 -> 24
A98: GMTD | B98: 2019 | I98: 211154716963
B99: 2020 | C99: 466605508681 | D99: 520717633415 | E99: 987323142096 | F99: 335120216073 | G99: 402384335106 | H99: 584938806990 | I99: 171579489556 | J99: -96956856318 | K99: 451221614 | L99: -105950046766 | M99: 408789510 | N99: 2000 | O99: =B99-N99 -> 20
B100: 2021 | C100: 493500638906 | D100: 579433997793 | E100: 1072934636699 | F100: 290368704875 | G100: 515861813615 | H100: 557072823084 | I100: 141833536671 | J100: -5856436266 | K100: 334357652 | L100: -27376369761 | M100: 1207974442 | N100: 2000 | O100: =B100-N100 -> 21
...

Sheet HASIL PERHITUNGAN
A1: Emiten | B1: Tahun | C1: DER | D1: TDR | E1: ROE | F1: TAN | G1: LIQ | H1: GRW | I1: SIZ | J1: TAX | K1: AGE | L1: NDTS
A2: APLN | B2: 2020 | C2: ='RAW DATA'!G3/'RAW DATA'!H3 -> 1.6764208 | D2: ='RAW DATA'!G3/'RAW DATA'!E3 -> 0.62636667 | E2: ='RAW DATA'!L3/'RAW DATA'!H3 -> 0.015864476 | F2: ='RAW DATA'!D3/'RAW DATA'!E3 -> 0.61579289 | G2: ='RAW DATA'!C3/'RAW DATA'!F3 -> 1.895883 | H2: =('RAW DATA'!I3-'RAW DATA'!I2)/'RAW DATA'!I2 -> 0.30688374 | I2: =LN('RAW DATA'!E3) -> 31.045179 | J2: ='RAW DATA'!K3/'RAW DATA'!J3 -> 0.17103105 | K2: =LN('RAW DATA'!O3) -> 2.3025851 | L2: ='RAW DATA'!M3/'RAW DATA'!E3 -> 0.0062102202
A3: APLN | B3: 2021 | C3: ='RAW DATA'!G4/'RAW DATA'!H4 -> 1.8094626 | D3: ='RAW DATA'!G4/'RAW DATA'!E4 -> 0.64406004 | E3: ='RAW DATA'!L4/'RAW DATA'!H4 -> -0.046037748 | F3: ='RAW DATA'!D4/'RAW DATA'!E4 -> 0.59613499 | G3: ='RAW DATA'!C4/'RAW DATA'!F4 -> 1.6349914 | H3: =('RAW DATA'!I4-'RAW DATA'!I3)/'RAW DATA'!I3 -> -0.1412497 | I3: =LN('RAW DATA'!E4) -> 31.019171 | J3: ='RAW DATA'!K4/'RAW DATA'!J4 -> 0.33095653 | K3: =LN('RAW DATA'!O4) -> 2.3978953 | L3: ='RAW DATA'!M4/'RAW DATA'!E4 -> 0.0096555749
A4: APLN | B4: 2022 | C4: ='RAW DATA'!G5/'RAW DATA'!H5 -> 1.2950112 | D4: ='RAW DATA'!G5/'RAW DATA'!E5 -> 0.56427227 | E4: ='RAW DATA'!L5/'RAW DATA'!H5 -> 0.18195591 | F4: ='RAW DATA'!D5/'RAW DATA'!E5 -> 0.60502226 | G4: ='RAW DATA'!C5/'RAW DATA'!F5 -> 1.9584646 | H4: =('RAW DATA'!I5-'RAW DATA'!I4)/'RAW DATA'!I4 -> 1.0355558 | I4: =LN('RAW DATA'!E5) -> 30.985049 | J4: ='RAW DATA'!K5/'RAW DATA'!J5 -> 0.08301229 | K4: =LN('RAW DATA'!O5) -> 2.4849066 | L4: ='RAW DATA'!M5/'RAW DATA'!E5 -> 0.0087857933
A5: APLN | B5: 2023 | C5: ='RAW DATA'!G6/'RAW DATA'!H6 -> 1.1059178 | D5: ='RAW DATA'!G6/'RAW DATA'!E6 -> 0.52514765 | E5: ='RAW DATA'!L6/'RAW DATA'!H6 -> 0.086572281 | F5: ='RAW DATA'!D6/'RAW DATA'!E6 -> 0.60777052 | G5: ='RAW DATA'!C6/'RAW DATA'!F6 -> 1.3012906 | H5: =('RAW DATA'!I6-'RAW DATA'!I5)/'RAW DATA'!I5 -> -0.46020933 | I5: =LN('RAW DATA'!E6) -> 30.974856 | J5: ='RAW DATA'!K6/'RAW DATA'!J6 -> 0.21232702 | K5: =LN('RAW DATA'!O6) -> 2.5649494 | L5: ='RAW DATA'!M6/'RAW DATA'!E6 -> 0.0085640861
A6: APLN | B6: 2024 | C6: ='RAW DATA'!G7/'RAW DATA'!H7 -> 0.89497103 | D6: ='RAW DATA'!G7/'RAW DATA'!E7 -> 0.47228745 | E6: ='RAW DATA'!L7/'RAW DATA'!H7 -> 0.055901345 | F6: ='RAW DATA'!D7/'RAW DATA'!E7 -> 0.58404072 | G6: ='RAW DATA'!C7/'RAW DATA'!F7 -> 2.4332274 | H6: =('RAW DATA'!I7-'RAW DATA'!I6)/'RAW DATA'!I6 -> 0.19246786 | I6: =LN('RAW DATA'!E7) -> 30.89371 | J6: ='RAW DATA'!K7/'RAW DATA'!J7 -> 0.14419424 | K6: =LN('RAW DATA'!O7) -> 2.6390573 | L6: ='RAW DATA'!M7/'RAW DATA'!E7 -> 0.0079384333
A7: ASRI | B7: 2020 | C7: ='RAW DATA'!G9/'RAW DATA'!H9 -> 1.2615044 | D7: ='RAW DATA'!G9/'RAW DATA'!E9 -> 0.55781647 | E7: ='RAW DATA'!L9/'RAW DATA'!H9 -> -0.11044125 | F7: ='RAW DATA'!D9/'RAW DATA'!E9 -> 0.8984303 | G7: ='RAW DATA'!C9/'RAW DATA'!F9 -> 0.67413769 | H7: =('RAW DATA'!I9-'RAW DATA'!I8)/'RAW DATA'!I8 -> -0.59338803 | I7: =LN('RAW DATA'!E9) -> 30.686286 | J7: ='RAW DATA'!K9/'RAW DATA'!J9 -> 0.65621463 | K7: =LN('RAW DATA'!O9) -> 2.5649494 | L7: ='RAW DATA'!M9/'RAW DATA'!E9 -> 0.0049441172
A8: ASRI | B8: 2021 | C8: ='RAW DATA'!G10/'RAW DATA'!H10 -> 1.3001012 | D8: ='RAW DATA'!G10/'RAW DATA'!E10 -> 0.56523652 | E8: ='RAW DATA'!L10/'RAW DATA'!H10 -> 0.014988194 | F8: ='RAW DATA'!D10/'RAW DATA'!E10 -> 0.86165738 | G8: ='RAW DATA'!C10/'RAW DATA'!F10 -> 0.83517301 | H8: =('RAW DATA'!I10-'RAW DATA'!I9)/'RAW DATA'!I9 -> 1.0147318 | I8: =LN('RAW DATA'!E10) -> 30.719058 | J8: ='RAW DATA'!K10/'RAW DATA'!J10 -> 0.078513216 | K8: =LN('RAW DATA'!O10) -> 2.6390573 | L8: ='RAW DATA'!M10/'RAW DATA'!E10 -> 0.0028504045
A9: ASRI | B9: 2022 | C9: ='RAW DATA'!G11/'RAW DATA'!H11 -> 1.0952468 | D9: ='RAW DATA'!G11/'RAW DATA'!E11 -> 0.52272926 | E9: ='RAW DATA'!L11/'RAW DATA'!H11 -> 0.10320433 | F9: ='RAW DATA'!D11/'RAW DATA'!E11 -> 0.83693482 | G9: ='RAW DATA'!C11/'RAW DATA'!F11 -> 0.97807109 | H9: =('RAW DATA'!I11-'RAW DATA'!I10)/'RAW DATA'!I10 -> 0.5781596 | I9: =LN('RAW DATA'!E11) -> 30.73556 | J9: ='RAW DATA'!K11/'RAW DATA'!J11 -> 0.05773463 | K9: =LN('RAW DATA'!O11) -> 2.7080502 | L9: ='RAW DATA'!M11/'RAW DATA'!E11 -> 0.00275433
A10: ASRI | B10: 2023 | C10: ='RAW DATA'!G12/'RAW DATA'!H12 -> 0.97283918 | D10: ='RAW DATA'!G12/'RAW DATA'!E12 -> 0.49311631 | E10: ='RAW DATA'!L12/'RAW DATA'!H12 -> 0.056572562 | F10: ='RAW DATA'!D12/'RAW DATA'!E12 -> 0.86934384 | G10: ='RAW DATA'!C12/'RAW DATA'!F12 -> 0.78773689 | H10: =('RAW DATA'!I12-'RAW DATA'!I11)/'RAW DATA'!I11 -> -0.11961989 | I10: =LN('RAW DATA'!E12) -> 30.732744 | J10: ='RAW DATA'!K12/'RAW DATA'!J12 -> 0.077696014 | K10: =LN('RAW DATA'!O12) -> 2.7725887 | L10: ='RAW DATA'!M12/'RAW DATA'!E12 -> 0.0022253201
A11: ASRI | B11: 2024 | C11: ='RAW DATA'!G13/'RAW DATA'!H13 -> 0.94244333 | D11: ='RAW DATA'!G13/'RAW DATA'!E13 -> 0.48518447 | E11: ='RAW DATA'!L13/'RAW DATA'!H13 -> 0.0057461233 | F11: ='RAW DATA'!D13/'RAW DATA'!E13 -> 0.87137364 | G11: ='RAW DATA'!C13/'RAW DATA'!F13 -> 0.76455951 | H11: =('RAW DATA'!I13-'RAW DATA'!I12)/'RAW DATA'!I12 -> -0.13212243 | I11: =LN('RAW DATA'!E13) -> 30.722928 | J11: ='RAW DATA'!K13/'RAW DATA'!J13 -> 0.084770199 | K11: =LN('RAW DATA'!O13) -> 2.8332133 | L11: ='RAW DATA'!M13/'RAW DATA'!E13 -> 0.0024504297
A12: BAPA | B12: 2020 | C12: ='RAW DATA'!G15/'RAW DATA'!H15 -> 0.060346124 | D12: ='RAW DATA'!G15/'RAW DATA'!E15 -> 0.056911722 | E12: ='RAW DATA'!L15/'RAW DATA'!H15 -> -0.027851028 | F12: ='RAW DATA'!D15/'RAW DATA'!E15 -> 0.81992589 | G12: ='RAW DATA'!C15/'RAW DATA'!F15 -> 3.4418337 | H12: =('RAW DATA'!I15-'RAW DATA'!I14)/'RAW DATA'!I14 -> -0.60720202 | I12: =LN('RAW DATA'!E15) -> 25.681251 | J12: ='RAW DATA'!K15/'RAW DATA'!J15 -> -0.1565004 | K12: =LN('RAW DATA'!O15) -> 2.4849066 | L12: ='RAW DATA'!M15/'RAW DATA'!E15 -> 0.0034452493
A13: BAPA | B13: 2021 | C13: ='RAW DATA'!G16/'RAW DATA'!H16 -> 0.054162316 | D13: ='RAW DATA'!G16/'RAW DATA'!E16 -> 0.051379484 | E13: ='RAW DATA'!L16/'RAW DATA'!H16 -> -0.015500429 | F13: ='RAW DATA'!D16/'RAW DATA'!E16 -> 0.82602569 | G13: ='RAW DATA'!C16/'RAW DATA'!F16 -> 3.5747239 | H13: =('RAW DATA'!I16-'RAW DATA'!I15)/'RAW DATA'!I15 -> -0.34921835 | I13: =LN('RAW DATA'!E16) -> 25.661839 | J13: ='RAW DATA'!K16/'RAW DATA'!J16 -> -0.16645987 | K13: =LN('RAW DATA'!O16) -> 2.5649494 | L13: ='RAW DATA'!M16/'RAW DATA'!E16 -> 0.0035167799
A14: BAPA | B14: 2022 | C14: ='RAW DATA'!G17/'RAW DATA'!H17 -> 0.051139713 | D14: ='RAW DATA'!G17/'RAW DATA'!E17 -> 0.04865168 | E14: ='RAW DATA'!L17/'RAW DATA'!H17 -> -0.02881039 | F14: ='RAW DATA'!D17/'RAW DATA'!E17 -> 0.83131733 | G14: ='RAW DATA'!C17/'RAW DATA'!F17 -> 3.5792152 | H14: =('RAW DATA'!I17-'RAW DATA'!I16)/'RAW DATA'!I16 -> -0.40013299 | I14: =LN('RAW DATA'!E17) -> 25.63175 | J14: ='RAW DATA'!K17/'RAW DATA'!J17 -> -0.061678463 | K14: =LN('RAW DATA'!O17) -> 2.6390573 | L14: ='RAW DATA'!M17/'RAW DATA'!E17 -> 0.0028896313
A15: BAPA | B15: 2023 | C15: ='RAW DATA'!G18/'RAW DATA'!H18 -> 0.072037154 | D15: ='RAW DATA'!G18/'RAW DATA'!E18 -> 0.067196509 | E15: ='RAW DATA'!L18/'RAW DATA'!H18 -> -0.022713297 | F15: ='RAW DATA'!D18/'RAW DATA'!E18 -> 0.82731607 | G15: ='RAW DATA'!C18/'RAW DATA'!F18 -> 2.71264 | H15: =('RAW DATA'!I18-'RAW DATA'!I17)/'RAW DATA'!I17 -> 1.1850929 | I15: =LN('RAW DATA'!E18) -> 25.62752 | J15: ='RAW DATA'!K18/'RAW DATA'!J18 -> -0.14391869 | K15: =LN('RAW DATA'!O18) -> 2.7080502 | L15: ='RAW DATA'!M18/'RAW DATA'!E18 -> 0.0037915292
A16: BAPA | B16: 2024 | C16: ='RAW DATA'!G19/'RAW DATA'!H19 -> 0.099969711 | D16: ='RAW DATA'!G19/'RAW DATA'!E19 -> 0.090884058 | E16: ='RAW DATA'!L19/'RAW DATA'!H19 -> -0.037908471 | F16: ='RAW DATA'!D19/'RAW DATA'!E19 -> 0.82076472 | G16: ='RAW DATA'!C19/'RAW DATA'!F19 -> 2.2092787 | H16: =('RAW DATA'!I19-'RAW DATA'!I18)/'RAW DATA'!I18 -> -0.49924166 | I16: =LN('RAW DATA'!E19) -> 25.611214 | J16: ='RAW DATA'!K19/'RAW DATA'!J19 -> -0.039460189 | K16: =LN('RAW DATA'!O19) -> 2.7725887 | L16: ='RAW DATA'!M19/'RAW DATA'!E19 -> 0.0035862733
A17: BCIP | B17: 2020 | C17: ='RAW DATA'!G21/'RAW DATA'!H21 -> 1.036007 | D17: ='RAW DATA'!G21/'RAW DATA'!E21 -> 0.50884256 | E17: ='RAW DATA'!L21/'RAW DATA'!H21 -> 0.029088787 | F17: ='RAW DATA'!D21/'RAW DATA'!E21 -> 0.56473831 | G17: ='RAW DATA'!C21/'RAW DATA'!F21 -> 1.2837069 | H17: =('RAW DATA'!I21-'RAW DATA'!I20)/'RAW DATA'!I20 -> -0.44196527 | I17: =LN('RAW DATA'!E21) -> 27.535902 | J17: ='RAW DATA'!K21/'RAW DATA'!J21 -> -0.38877707 | K17: =LN('RAW DATA'!O21) -> 2.3978953 | L17: ='RAW DATA'!M21/'RAW DATA'!E21 -> 0.0025539871
A18: BCIP | B18: 2021 | C18: ='RAW DATA'!G22/'RAW DATA'!H22 -> 0.98584454 | D18: ='RAW DATA'!G22/'RAW DATA'!E22 -> 0.49643591 | E18: ='RAW DATA'!L22/'RAW DATA'!H22 -> 0.00027799392 | F18: ='RAW DATA'!D22/'RAW DATA'!E22 -> 0.60799525 | G18: ='RAW DATA'!C22/'RAW DATA'!F22 -> 3.4380362 | H18: =('RAW DATA'!I22-'RAW DATA'!I21)/'RAW DATA'!I21 -> -0.17422826 | I18: =LN('RAW DATA'!E22) -> 27.511193 | J18: ='RAW DATA'!K22/'RAW DATA'!J22 -> -1.2509857 | K18: =LN('RAW DATA'!O22) -> 2.4849066 | L18: ='RAW DATA'!M22/'RAW DATA'!E22 -> 0.0032887296
A19: BCIP | B19: 2022 | C19: ='RAW DATA'!G23/'RAW DATA'!H23 -> 0.90629161 | D19: ='RAW DATA'!G23/'RAW DATA'!E23 -> 0.47542129 | E19: ='RAW DATA'!L23/'RAW DATA'!H23 -> 0.03679571 | F19: ='RAW DATA'!D23/'RAW DATA'!E23 -> 0.58562553 | G19: ='RAW DATA'!C23/'RAW DATA'!F23 -> 4.4724017 | H19: =('RAW DATA'!I23-'RAW DATA'!I22)/'RAW DATA'!I22 -> 0.55179177 | I19: =LN('RAW DATA'!E23) -> 27.507762 | J19: ='RAW DATA'!K23/'RAW DATA'!J23 -> 0.33435995 | K19: =LN('RAW DATA'!O23) -> 2.5649494 | L19: ='RAW DATA'!M23/'RAW DATA'!E23 -> 0.0025693301
A20: BCIP | B20: 2023 | C20: ='RAW DATA'!G24/'RAW DATA'!H24 -> 0.89321119 | D20: ='RAW DATA'!G24/'RAW DATA'!E24 -> 0.47179691 | E20: ='RAW DATA'!L24/'RAW DATA'!H24 -> 0.035948031 | F20: ='RAW DATA'!D24/'RAW DATA'!E24 -> 0.58261224 | G20: ='RAW DATA'!C24/'RAW DATA'!F24 -> 4.4979731 | H20: =('RAW DATA'!I24-'RAW DATA'!I23)/'RAW DATA'!I23 -> 0.0059736708 | I20: =LN('RAW DATA'!E24) -> 27.537405 | J20: ='RAW DATA'!K24/'RAW DATA'!J24 -> 0.34050627 | K20: =LN('RAW DATA'!O24) -> 2.6390573 | L20: ='RAW DATA'!M24/'RAW DATA'!E24 -> 0.0023739532
A21: BCIP | B21: 2024 | C21: ='RAW DATA'!G25/'RAW DATA'!H25 -> 0.8541399 | D21: ='RAW DATA'!G25/'RAW DATA'!E25 -> 0.46066637 | E21: ='RAW DATA'!L25/'RAW DATA'!H25 -> 0.030929403 | F21: ='RAW DATA'!D25/'RAW DATA'!E25 -> 0.60801363 | G21: ='RAW DATA'!C25/'RAW DATA'!F25 -> 3.4899278 | H21: =('RAW DATA'!I25-'RAW DATA'!I24)/'RAW DATA'!I24 -> 0.060435044 | I21: =LN('RAW DATA'!E25) -> 27.542735 | J21: ='RAW DATA'!K25/'RAW DATA'!J25 -> 0.48377585 | K21: =LN('RAW DATA'!O25) -> 2.7080502 | L21: ='RAW DATA'!M25/'RAW DATA'!E25 -> 0.0029345281
A22: BEST | B22: 2020 | C22: ='RAW DATA'!G27/'RAW DATA'!H27 -> 0.44197261 | D22: ='RAW DATA'!G27/'RAW DATA'!E27 -> 0.30650555 | E22: ='RAW DATA'!L27/'RAW DATA'!H27 -> -0.026446799 | F22: ='RAW DATA'!D27/'RAW DATA'!E27 -> 0.56657925 | G22: ='RAW DATA'!C27/'RAW DATA'!F27 -> 10.526264 | H22: =('RAW DATA'!I27-'RAW DATA'!I26)/'RAW DATA'!I26 -> -0.74507197 | I22: =LN('RAW DATA'!E27) -> 29.468738 | J22: ='RAW DATA'!K27/'RAW DATA'!J27 -> 0.26254512 | K22: =LN('RAW DATA'!O27) -> 2.0794415 | L22: ='RAW DATA'!M27/'RAW DATA'!E27 -> 0.0025263183
A23: BEST | B23: 2021 | C23: ='RAW DATA'!G28/'RAW DATA'!H28 -> 0.4080943 | D23: ='RAW DATA'!G28/'RAW DATA'!E28 -> 0.28982029 | E23: ='RAW DATA'!L28/'RAW DATA'!H28 -> -0.016557225 | F23: ='RAW DATA'!D28/'RAW DATA'!E28 -> 0.58441514 | G23: ='RAW DATA'!C28/'RAW DATA'!F28 -> 5.8086003 | H23: =('RAW DATA'!I28-'RAW DATA'!I27)/'RAW DATA'!I27 -> -0.051522403 | I23: =LN('RAW DATA'!E28) -> 29.430453 | J23: ='RAW DATA'!K28/'RAW DATA'!J28 -> 0.2083712 | K23: =LN('RAW DATA'!O28) -> 2.1972246 | L23: ='RAW DATA'!M28/'RAW DATA'!E28 -> 0.0023941416
A24: BEST | B24: 2022 | C24: ='RAW DATA'!G29/'RAW DATA'!H29 -> 0.4042886 | D24: ='RAW DATA'!G29/'RAW DATA'!E29 -> 0.28789566 | E24: ='RAW DATA'!L29/'RAW DATA'!H29 -> 0.0077924318 | F24: ='RAW DATA'!D29/'RAW DATA'!E29 -> 0.57437492 | G24: ='RAW DATA'!C29/'RAW DATA'!F29 -> 9.2413973 | H24: =('RAW DATA'!I29-'RAW DATA'!I28)/'RAW DATA'!I28 -> 1.3618345 | I24: =LN('RAW DATA'!E29) -> 29.435774 | J24: ='RAW DATA'!K29/'RAW DATA'!J29 -> 0.062946285 | K24: =LN('RAW DATA'!O29) -> 2.3025851 | L24: ='RAW DATA'!M29/'RAW DATA'!E29 -> 0.0022064301
A25: BEST | B25: 2023 | C25: ='RAW DATA'!G30/'RAW DATA'!H30 -> 0.35997695 | D25: ='RAW DATA'!G30/'RAW DATA'!E30 -> 0.26469342 | E25: ='RAW DATA'!L30/'RAW DATA'!H30 -> 0.0090499106 | F25: ='RAW DATA'!D30/'RAW DATA'!E30 -> 0.59100335 | G25: ='RAW DATA'!C30/'RAW DATA'!F30 -> 10.030641 | H25: =('RAW DATA'!I30-'RAW DATA'!I29)/'RAW DATA'!I29 -> 0.0027280251 | I25: =LN('RAW DATA'!E30) -> 29.412748 | J25: ='RAW DATA'!K30/'RAW DATA'!J30 -> 0.057826194 | K25: =LN('RAW DATA'!O30) -> 2.3978953 | L25: ='RAW DATA'!M30/'RAW DATA'!E30 -> 0.002353778
A26: BEST | B26: 2024 | C26: ='RAW DATA'!G31/'RAW DATA'!H31 -> 0.31653775 | D26: ='RAW DATA'!G31/'RAW DATA'!E31 -> 0.24043196 | E26: ='RAW DATA'!L31/'RAW DATA'!H31 -> 0.013235459 | F26: ='RAW DATA'!D31/'RAW DATA'!E31 -> 0.60778675 | G26: ='RAW DATA'!C31/'RAW DATA'!F31 -> 9.9152985 | H26: =('RAW DATA'!I31-'RAW DATA'!I30)/'RAW DATA'!I30 -> -0.15932893 | I26: =LN('RAW DATA'!E31) -> 29.393559 | J26: ='RAW DATA'!K31/'RAW DATA'!J31 -> 0.077906944 | K26: =LN('RAW DATA'!O31) -> 2.4849066 | L26: ='RAW DATA'!M31/'RAW DATA'!E31 -> 0.0024049451
A27: BIPP | B27: 2020 | C27: ='RAW DATA'!G33/'RAW DATA'!H33 -> 0.76190902 | D27: ='RAW DATA'!G33/'RAW DATA'!E33 -> 0.4324338 | E27: ='RAW DATA'!L33/'RAW DATA'!H33 -> 0.077934932 | F27: ='RAW DATA'!D33/'RAW DATA'!E33 -> 0.53566564 | G27: ='RAW DATA'!C33/'RAW DATA'!F33 -> 2.6091824 | H27: =('RAW DATA'!I33-'RAW DATA'!I32)/'RAW DATA'!I32 -> 0.47561786 | I27: =LN('RAW DATA'!E33) -> 28.38551 | J27: ='RAW DATA'!K33/'RAW DATA'!J33 -> 0.11749504 | K27: =LN('RAW DATA'!O33) -> 3.2188758 | L27: ='RAW DATA'!M33/'RAW DATA'!E33 -> 0.0033439885
A28: BIPP | B28: 2021 | C28: ='RAW DATA'!G34/'RAW DATA'!H34 -> 0.85383602 | D28: ='RAW DATA'!G34/'RAW DATA'!E34 -> 0.46057796 | E28: ='RAW DATA'!L34/'RAW DATA'!H34 -> 0.017726056 | F28: ='RAW DATA'!D34/'RAW DATA'!E34 -> 0.65012639 | G28: ='RAW DATA'!C34/'RAW DATA'!F34 -> 1.7098388 | H28: =('RAW DATA'!I34-'RAW DATA'!I33)/'RAW DATA'!I33 -> -0.4451312 | I28: =LN('RAW DATA'!E34) -> 28.346557 | J28: ='RAW DATA'!K34/'RAW DATA'!J34 -> 0.17927755 | K28: =LN('RAW DATA'!O34) -> 3.2580965 | L28: ='RAW DATA'!M34/'RAW DATA'!E34 -> 0.0033473261
A29: BIPP | B29: 2022 | C29: ='RAW DATA'!G35/'RAW DATA'!H35 -> 0.74530509 | D29: ='RAW DATA'!G35/'RAW DATA'!E35 -> 0.42703427 | E29: ='RAW DATA'!L35/'RAW DATA'!H35 -> 0.023359343 | F29: ='RAW DATA'!D35/'RAW DATA'!E35 -> 0.69644782 | G29: ='RAW DATA'!C35/'RAW DATA'!F35 -> 2.3138455 | H29: =('RAW DATA'!I35-'RAW DATA'!I34)/'RAW DATA'!I34 -> 0.11336901 | I29: =LN('RAW DATA'!E35) -> 28.266717 | J29: ='RAW DATA'!K35/'RAW DATA'!J35 -> 0.16576874 | K29: =LN('RAW DATA'!O35) -> 3.2958369 | L29: ='RAW DATA'!M35/'RAW DATA'!E35 -> 0.004230674
A30: BIPP | B30: 2023 | C30: ='RAW DATA'!G36/'RAW DATA'!H36 -> 0.84666108 | D30: ='RAW DATA'!G36/'RAW DATA'!E36 -> 0.45848212 | E30: ='RAW DATA'!L36/'RAW DATA'!H36 -> -0.00424613 | F30: ='RAW DATA'!D36/'RAW DATA'!E36 -> 0.7379595 | G30: ='RAW DATA'!C36/'RAW DATA'!F36 -> 1.9803018 | H30: =('RAW DATA'!I36-'RAW DATA'!I35)/'RAW DATA'!I35 -> -0.19325341 | I30: =LN('RAW DATA'!E36) -> 28.29645 | J30: ='RAW DATA'!K36/'RAW DATA'!J36 -> 0.17288773 | K30: =LN('RAW DATA'!O36) -> 3.3322045 | L30: ='RAW DATA'!M36/'RAW DATA'!E36 -> 0.005402426
A31: BIPP | B31: 2024 | C31: ='RAW DATA'!G37/'RAW DATA'!H37 -> 0.81891949 | D31: ='RAW DATA'!G37/'RAW DATA'!E37 -> 0.45022306 | E31: ='RAW DATA'!L37/'RAW DATA'!H37 -> -0.0063049148 | F31: ='RAW DATA'!D37/'RAW DATA'!E37 -> 0.77659886 | G31: ='RAW DATA'!C37/'RAW DATA'!F37 -> 1.82182 | H31: =('RAW DATA'!I37-'RAW DATA'!I36)/'RAW DATA'!I36 -> -0.020856834 | I31: =LN('RAW DATA'!E37) -> 28.252141 | J31: ='RAW DATA'!K37/'RAW DATA'!J37 -> 0.27943139 | K31: =LN('RAW DATA'!O37) -> 3.3672958 | L31: ='RAW DATA'!M37/'RAW DATA'!E37 -> 0.00601731
A32: BKDP | B32: 2020 | C32: ='RAW DATA'!G39/'RAW DATA'!H39 -> 0.64302803 | D32: ='RAW DATA'!G39/'RAW DATA'!E39 -> 0.39136766 | E32: ='RAW DATA'!L39/'RAW DATA'!H39 -> -0.064508872 | F32: ='RAW DATA'!D39/'RAW DATA'!E39 -> 0.89008358 | G32: ='RAW DATA'!C39/'RAW DATA'!F39 -> 0.50638245 | H32: =('RAW DATA'!I39-'RAW DATA'!I38)/'RAW DATA'!I38 -> -0.44394544 | I32: =LN('RAW DATA'!E39) -> 27.396362 | J32: ='RAW DATA'!K39/'RAW DATA'!J39 -> -0.043149661 | K32: =LN('RAW DATA'!O39) -> 2.5649494 | L32: ='RAW DATA'!M39/'RAW DATA'!E39 -> 0.0038675716
A33: BKDP | B33: 2021 | C33: ='RAW DATA'!G40/'RAW DATA'!H40 -> 0.73354757 | D33: ='RAW DATA'!G40/'RAW DATA'!E40 -> 0.42314822 | E33: ='RAW DATA'!L40/'RAW DATA'!H40 -> -0.081198399 | F33: ='RAW DATA'!D40/'RAW DATA'!E40 -> 0.89334734 | G33: ='RAW DATA'!C40/'RAW DATA'!F40 -> 0.76108393 | H33: =('RAW DATA'!I40-'RAW DATA'!I39)/'RAW DATA'!I39 -> 0.19649038 | I33: =LN('RAW DATA'!E40) -> 27.375018 | J33: ='RAW DATA'!K40/'RAW DATA'!J40 -> -0.078875747 | K33: =LN('RAW DATA'!O40) -> 2.6390573 | L33: ='RAW DATA'!M40/'RAW DATA'!E40 -> 0.0017847516
A34: BKDP | B34: 2022 | C34: ='RAW DATA'!G41/'RAW DATA'!H41 -> 0.83062913 | D34: ='RAW DATA'!G41/'RAW DATA'!E41 -> 0.45373971 | E34: ='RAW DATA'!L41/'RAW DATA'!H41 -> -0.079874799 | F34: ='RAW DATA'!D41/'RAW DATA'!E41 -> 0.91125283 | G34: ='RAW DATA'!C41/'RAW DATA'!F41 -> 0.51827355 | H34: =('RAW DATA'!I41-'RAW DATA'!I40)/'RAW DATA'!I40 -> 0.11255586 | I34: =LN('RAW DATA'!E41) -> 27.351968 | J34: ='RAW DATA'!K41/'RAW DATA'!J41 -> -0.12520481 | K34: =LN('RAW DATA'!O41) -> 2.7080502 | L34: ='RAW DATA'!M41/'RAW DATA'!E41 -> 0.0014389771
A35: BKDP | B35: 2023 | C35: ='RAW DATA'!G42/'RAW DATA'!H42 -> 0.98539888 | D35: ='RAW DATA'!G42/'RAW DATA'!E42 -> 0.49632288 | E35: ='RAW DATA'!L42/'RAW DATA'!H42 -> -0.090583578 | F35: ='RAW DATA'!D42/'RAW DATA'!E42 -> 0.92216362 | G35: ='RAW DATA'!C42/'RAW DATA'!F42 -> 0.37130931 | H35: =('RAW DATA'!I42-'RAW DATA'!I41)/'RAW DATA'!I41 -> 0.19878353 | I35: =LN('RAW DATA'!E42) -> 27.354264 | J35: ='RAW DATA'!K42/'RAW DATA'!J42 -> -0.10122786 | K35: =LN('RAW DATA'!O42) -> 2.7725887 | L35: ='RAW DATA'!M42/'RAW DATA'!E42 -> 0.0013752269
A36: BKDP | B36: 2024 | C36: ='RAW DATA'!G43/'RAW DATA'!H43 -> 1.1756089 | D36: ='RAW DATA'!G43/'RAW DATA'!E43 -> 0.54035855 | E36: ='RAW DATA'!L43/'RAW DATA'!H43 -> -0.10386882 | F36: ='RAW DATA'!D43/'RAW DATA'!E43 -> 0.92541704 | G36: ='RAW DATA'!C43/'RAW DATA'!F43 -> 0.30593421 | H36: =('RAW DATA'!I43-'RAW DATA'!I42)/'RAW DATA'!I42 -> -0.022135104 | I36: =LN('RAW DATA'!E43) -> 27.346328 | J36: ='RAW DATA'!K43/'RAW DATA'!J43 -> -0.10183739 | K36: =LN('RAW DATA'!O43) -> 2.8332133 | L36: ='RAW DATA'!M43/'RAW DATA'!E43 -> 0.0013493653
A37: BKSL | B37: 2020 | C37: ='RAW DATA'!G45/'RAW DATA'!H45 -> 0.79229781 | D37: ='RAW DATA'!G45/'RAW DATA'!E45 -> 0.44205701 | E37: ='RAW DATA'!L45/'RAW DATA'!H45 -> -0.05427282 | F37: ='RAW DATA'!D45/'RAW DATA'!E45 -> 0.75022189 | G37: ='RAW DATA'!C45/'RAW DATA'!F45 -> 1.4032123 | H37: =('RAW DATA'!I45-'RAW DATA'!I44)/'RAW DATA'!I44 -> -0.52508173 | I37: =LN('RAW DATA'!E45) -> 30.541807 | J37: ='RAW DATA'!K45/'RAW DATA'!J45 -> 0.95081986 | K37: =LN('RAW DATA'!O45) -> 3.1354942 | L37: ='RAW DATA'!M45/'RAW DATA'!E45 -> 0.00072718216
A38: BKSL | B38: 2021 | C38: ='RAW DATA'!G46/'RAW DATA'!H46 -> 0.5882997 | D38: ='RAW DATA'!G46/'RAW DATA'!E46 -> 0.3703959 | E38: ='RAW DATA'!L46/'RAW DATA'!H46 -> 0.021864321 | F38: ='RAW DATA'!D46/'RAW DATA'!E46 -> 0.72052655 | G38: ='RAW DATA'!C46/'RAW DATA'!F46 -> 2.8337615 | H38: =('RAW DATA'!I46-'RAW DATA'!I45)/'RAW DATA'!I45 -> 1.0155249 | I38: =LN('RAW DATA'!E46) -> 30.443731 | J38: ='RAW DATA'!K46/'RAW DATA'!J46 -> 0.1802377 | K38: =LN('RAW DATA'!O46) -> 3.1780538 | L38: ='RAW DATA'!M46/'RAW DATA'!E46 -> 0.00070482992
A39: BKSL | B39: 2022 | C39: ='RAW DATA'!G47/'RAW DATA'!H47 -> 0.61982164 | D39: ='RAW DATA'!G47/'RAW DATA'!E47 -> 0.38264808 | E39: ='RAW DATA'!L47/'RAW DATA'!H47 -> -0.016185157 | F39: ='RAW DATA'!D47/'RAW DATA'!E47 -> 0.73198376 | G39: ='RAW DATA'!C47/'RAW DATA'!F47 -> 2.0220317 | H39: =('RAW DATA'!I47-'RAW DATA'!I46)/'RAW DATA'!I46 -> -0.26178394 | I39: =LN('RAW DATA'!E47) -> 30.447732 | J39: ='RAW DATA'!K47/'RAW DATA'!J47 -> 0.054173659 | K39: =LN('RAW DATA'!O47) -> 3.2188758 | L39: ='RAW DATA'!M47/'RAW DATA'!E47 -> 0.00075609176
A40: BKSL | B40: 2023 | C40: ='RAW DATA'!G48/'RAW DATA'!H48 -> 0.31343825 | D40: ='RAW DATA'!G48/'RAW DATA'!E48 -> 0.2386395 | E40: ='RAW DATA'!L48/'RAW DATA'!H48 -> 0.020991197 | F40: ='RAW DATA'!D48/'RAW DATA'!E48 -> 0.82026927 | G40: ='RAW DATA'!C48/'RAW DATA'!F48 -> 1.1677575 | H40: =('RAW DATA'!I48-'RAW DATA'!I47)/'RAW DATA'!I47 -> 1.5586195 | I40: =LN('RAW DATA'!E48) -> 30.621081 | J40: ='RAW DATA'!K48/'RAW DATA'!J48 -> 0.085304767 | K40: =LN('RAW DATA'!O48) -> 3.2580965 | L40: ='RAW DATA'!M48/'RAW DATA'!E48 -> 0.00082457669
A41: BKSL | B41: 2024 | C41: ='RAW DATA'!G49/'RAW DATA'!H49 -> 0.39819605 | D41: ='RAW DATA'!G49/'RAW DATA'!E49 -> 0.28479272 | E41: ='RAW DATA'!L49/'RAW DATA'!H49 -> 0.00091923995 | F41: ='RAW DATA'!D49/'RAW DATA'!E49 -> 0.82239797 | G41: ='RAW DATA'!C49/'RAW DATA'!F49 -> 0.94440044 | H41: =('RAW DATA'!I49-'RAW DATA'!I48)/'RAW DATA'!I48 -> -0.56744248 | I41: =LN('RAW DATA'!E49) -> 30.68447 | J41: ='RAW DATA'!K49/'RAW DATA'!J49 -> 0.47544761 | K41: =LN('RAW DATA'!O49) -> 3.2958369 | L41: ='RAW DATA'!M49/'RAW DATA'!E49 -> 0.00084071116
A42: BSDE | B42: 2020 | C42: ='RAW DATA'!G51/'RAW DATA'!H51 -> 0.7656217 | D42: ='RAW DATA'!G51/'RAW DATA'!E51 -> 0.43362726 | E42: ='RAW DATA'!L51/'RAW DATA'!H51 -> 0.014106245 | F42: ='RAW DATA'!D51/'RAW DATA'!E51 -> 0.53396435 | G42: ='RAW DATA'!C51/'RAW DATA'!F51 -> 2.3971145 | H42: =('RAW DATA'!I51-'RAW DATA'!I50)/'RAW DATA'!I50 -> -0.12763476 | I42: =LN('RAW DATA'!E51) -> 31.739645 | J42: ='RAW DATA'!K51/'RAW DATA'!J51 -> 0.11997495 | K42: =LN('RAW DATA'!O51) -> 2.4849066 | L42: ='RAW DATA'!M51/'RAW DATA'!E51 -> 0.0013153735
A43: BSDE | B43: 2021 | C43: ='RAW DATA'!G52/'RAW DATA'!H52 -> 0.71254797 | D43: ='RAW DATA'!G52/'RAW DATA'!E52 -> 0.41607475 | E43: ='RAW DATA'!L52/'RAW DATA'!H52 -> 0.042872154 | F43: ='RAW DATA'!D52/'RAW DATA'!E52 -> 0.53802033 | G43: ='RAW DATA'!C52/'RAW DATA'!F52 -> 2.5891717 | H43: =('RAW DATA'!I52-'RAW DATA'!I51)/'RAW DATA'!I51 -> 0.23852308 | I43: =LN('RAW DATA'!E52) -> 31.749566 | J43: ='RAW DATA'!K52/'RAW DATA'!J52 -> 0.1024398 | K43: =LN('RAW DATA'!O52) -> 2.5649494 | L43: ='RAW DATA'!M52/'RAW DATA'!E52 -> 0.0012471832
A44: BSDE | B44: 2022 | C44: ='RAW DATA'!G53/'RAW DATA'!H53 -> 0.70846782 | D44: ='RAW DATA'!G53/'RAW DATA'!E53 -> 0.41468023 | E44: ='RAW DATA'!L53/'RAW DATA'!H53 -> 0.069834542 | F44: ='RAW DATA'!D53/'RAW DATA'!E53 -> 0.54481619 | G44: ='RAW DATA'!C53/'RAW DATA'!F53 -> 2.6106994 | H44: =('RAW DATA'!I53-'RAW DATA'!I52)/'RAW DATA'!I52 -> 0.33713186 | I44: =LN('RAW DATA'!E53) -> 31.805399 | J44: ='RAW DATA'!K53/'RAW DATA'!J53 -> 0.091527432 | K44: =LN('RAW DATA'!O53) -> 2.6390573 | L44: ='RAW DATA'!M53/'RAW DATA'!E53 -> 0.001144296
A45: BSDE | B45: 2023 | C45: ='RAW DATA'!G54/'RAW DATA'!H54 -> 0.62196786 | D45: ='RAW DATA'!G54/'RAW DATA'!E54 -> 0.38346497 | E45: ='RAW DATA'!L54/'RAW DATA'!H54 -> 0.054839074 | F45: ='RAW DATA'!D54/'RAW DATA'!E54 -> 0.56043914 | G45: ='RAW DATA'!C54/'RAW DATA'!F54 -> 2.4689464 | H45: =('RAW DATA'!I54-'RAW DATA'!I53)/'RAW DATA'!I53 -> 0.12736689 | I45: =LN('RAW DATA'!E54) -> 31.833138 | J45: ='RAW DATA'!K54/'RAW DATA'!J54 -> 0.13706888 | K45: =LN('RAW DATA'!O54) -> 2.7080502 | L45: ='RAW DATA'!M54/'RAW DATA'!E54 -> 0.0010292083
A46: BSDE | B46: 2024 | C46: ='RAW DATA'!G55/'RAW DATA'!H55 -> 0.60660246 | D46: ='RAW DATA'!G55/'RAW DATA'!E55 -> 0.37756849 | E46: ='RAW DATA'!L55/'RAW DATA'!H55 -> 0.1039252 | F46: ='RAW DATA'!D55/'RAW DATA'!E55 -> 0.59359207 | G46: ='RAW DATA'!C55/'RAW DATA'!F55 -> 2.1555462 | H46: =('RAW DATA'!I55-'RAW DATA'!I54)/'RAW DATA'!I54 -> 0.19563249 | I46: =LN('RAW DATA'!E55) -> 31.962062 | J46: ='RAW DATA'!K55/'RAW DATA'!J55 -> 0.09692625 | K46: =LN('RAW DATA'!O55) -> 2.7725887 | L46: ='RAW DATA'!M55/'RAW DATA'!E55 -> 0.0011347797
A47: CTRA | B47: 2020 | C47: ='RAW DATA'!G57/'RAW DATA'!H57 -> 1.2486109 | D47: ='RAW DATA'!G57/'RAW DATA'!E57 -> 0.55528099 | E47: ='RAW DATA'!L57/'RAW DATA'!H57 -> 0.078515469 | F47: ='RAW DATA'!D57/'RAW DATA'!E57 -> 0.47406706 | G47: ='RAW DATA'!C57/'RAW DATA'!F57 -> 1.7783495 | H47: =('RAW DATA'!I57-'RAW DATA'!I56)/'RAW DATA'!I56 -> 0.060789379 | I47: =LN('RAW DATA'!E57) -> 31.301105 | J47: ='RAW DATA'!K57/'RAW DATA'!J57 -> 0.10892194 | K47: =LN('RAW DATA'!O57) -> 3.2580965 | L47: ='RAW DATA'!M57/'RAW DATA'!E57 -> 0.0041427391
A48: CTRA | B48: 2021 | C48: ='RAW DATA'!G58/'RAW DATA'!H58 -> 1.0969371 | D48: ='RAW DATA'!G58/'RAW DATA'!E58 -> 0.52311397 | E48: ='RAW DATA'!L58/'RAW DATA'!H58 -> 0.10764643 | F48: ='RAW DATA'!D58/'RAW DATA'!E58 -> 0.46108443 | G48: ='RAW DATA'!C58/'RAW DATA'!F58 -> 1.9990961 | H48: =('RAW DATA'!I58-'RAW DATA'!I57)/'RAW DATA'!I57 -> 0.20554678 | I48: =LN('RAW DATA'!E58) -> 31.336473 | J48: ='RAW DATA'!K58/'RAW DATA'!J58 -> 0.091753885 | K48: =LN('RAW DATA'!O58) -> 3.2958369 | L48: ='RAW DATA'!M58/'RAW DATA'!E58 -> 0.0040052708
A49: CTRA | B49: 2022 | C49: ='RAW DATA'!G59/'RAW DATA'!H59 -> 1.0001311 | D49: ='RAW DATA'!G59/'RAW DATA'!E59 -> 0.50003277 | E49: ='RAW DATA'!L59/'RAW DATA'!H59 -> 0.095269221 | F49: ='RAW DATA'!D59/'RAW DATA'!E59 -> 0.43534546 | G49: ='RAW DATA'!C59/'RAW DATA'!F59 -> 2.1957467 | H49: =('RAW DATA'!I59-'RAW DATA'!I58)/'RAW DATA'!I58 -> -0.06196029 | I49: =LN('RAW DATA'!E59) -> 31.369467 | J49: ='RAW DATA'!K59/'RAW DATA'!J59 -> 0.10009221 | K49: =LN('RAW DATA'!O59) -> 3.3322045 | L49: ='RAW DATA'!M59/'RAW DATA'!E59 -> 0.0039647545
A50: CTRA | B50: 2023 | C50: ='RAW DATA'!G60/'RAW DATA'!H60 -> 0.94986823 | D50: ='RAW DATA'!G60/'RAW DATA'!E60 -> 0.48714483 | E50: ='RAW DATA'!L60/'RAW DATA'!H60 -> 0.084377855 | F50: ='RAW DATA'!D60/'RAW DATA'!E60 -> 0.41635028 | G50: ='RAW DATA'!C60/'RAW DATA'!F60 -> 2.4232351 | H50: =('RAW DATA'!I60-'RAW DATA'!I59)/'RAW DATA'!I59 -> 0.012954487 | I50: =LN('RAW DATA'!E60) -> 31.417826 | J50: ='RAW DATA'!K60/'RAW DATA'!J60 -> 0.10393085 | K50: =LN('RAW DATA'!O60) -> 3.3672958 | L50: ='RAW DATA'!M60/'RAW DATA'!E60 -> 0.0041049556
A51: CTRA | B51: 2024 | C51: ='RAW DATA'!G61/'RAW DATA'!H61 -> 0.91030151 | D51: ='RAW DATA'!G61/'RAW DATA'!E61 -> 0.47652243 | E51: ='RAW DATA'!L61/'RAW DATA'!H61 -> 0.09457391 | F51: ='RAW DATA'!D61/'RAW DATA'!E61 -> 0.43793585 | G51: ='RAW DATA'!C61/'RAW DATA'!F61 -> 1.9859885 | H51: =('RAW DATA'!I61-'RAW DATA'!I60)/'RAW DATA'!I60 -> 0.21011642 | I51: =LN('RAW DATA'!E61) -> 31.481652 | J51: ='RAW DATA'!K61/'RAW DATA'!J61 -> 0.10958733 | K51: =LN('RAW DATA'!O61) -> 3.4011974 | L51: ='RAW DATA'!M61/'RAW DATA'!E61 -> 0.0042960951
A52: DART | B52: 2020 | C52: ='RAW DATA'!G63/'RAW DATA'!H63 -> 1.2841018 | D52: ='RAW DATA'!G63/'RAW DATA'!E63 -> 0.56219113 | E52: ='RAW DATA'!L63/'RAW DATA'!H63 -> -0.13732263 | F52: ='RAW DATA'!D63/'RAW DATA'!E63 -> 0.97260135 | G52: ='RAW DATA'!C63/'RAW DATA'!F63 -> 0.2992885 | H52: =('RAW DATA'!I63-'RAW DATA'!I62)/'RAW DATA'!I62 -> -0.29756754 | I52: =LN('RAW DATA'!E63) -> 29.526558 | J52: ='RAW DATA'!K63/'RAW DATA'!J63 -> -0.098090453 | K52: =LN('RAW DATA'!O63) -> 3.4011974 | L52: ='RAW DATA'!M63/'RAW DATA'!E63 -> 0.010436423
A53: DART | B53: 2021 | C53: ='RAW DATA'!G64/'RAW DATA'!H64 -> 1.6381447 | D53: ='RAW DATA'!G64/'RAW DATA'!E64 -> 0.62094574 | E53: ='RAW DATA'!L64/'RAW DATA'!H64 -> -0.16427284 | F53: ='RAW DATA'!D64/'RAW DATA'!E64 -> 0.97139735 | G53: ='RAW DATA'!C64/'RAW DATA'!F64 -> 0.14676202 | H53: =('RAW DATA'!I64-'RAW DATA'!I63)/'RAW DATA'!I63 -> -0.10354075 | I53: =LN('RAW DATA'!E64) -> 29.518702 | J53: ='RAW DATA'!K64/'RAW DATA'!J64 -> -0.036968077 | K53: =LN('RAW DATA'!O64) -> 3.4339872 | L53: ='RAW DATA'!M64/'RAW DATA'!E64 -> 0.0095860547
A54: DART | B54: 2022 | C54: ='RAW DATA'!G65/'RAW DATA'!H65 -> 2.1035569 | D54: ='RAW DATA'!G65/'RAW DATA'!E65 -> 0.67778905 | E54: ='RAW DATA'!L65/'RAW DATA'!H65 -> -0.20225225 | F54: ='RAW DATA'!D65/'RAW DATA'!E65 -> 0.97798322 | G54: ='RAW DATA'!C65/'RAW DATA'!F65 -> 0.14287907 | H54: =('RAW DATA'!I65-'RAW DATA'!I64)/'RAW DATA'!I64 -> 0.1362326 | I54: =LN('RAW DATA'!E65) -> 29.497065 | J54: ='RAW DATA'!K65/'RAW DATA'!J65 -> -0.38439993 | K54: =LN('RAW DATA'!O65) -> 3.4657359 | L54: ='RAW DATA'!M65/'RAW DATA'!E65 -> 0.0091524665
A55: DART | B55: 2023 | C55: ='RAW DATA'!G66/'RAW DATA'!H66 -> 2.6335139 | D55: ='RAW DATA'!G66/'RAW DATA'!E66 -> 0.72478432 | E55: ='RAW DATA'!L66/'RAW DATA'!H66 -> -0.19775196 | F55: ='RAW DATA'!D66/'RAW DATA'!E66 -> 0.98035089 | G55: ='RAW DATA'!C66/'RAW DATA'!F66 -> 0.15070804 | H55: =('RAW DATA'!I66-'RAW DATA'!I65)/'RAW DATA'!I65 -> 0.31211097 | I55: =LN('RAW DATA'!E66) -> 29.474261 | J55: ='RAW DATA'!K66/'RAW DATA'!J66 -> 1.1129453 | K55: =LN('RAW DATA'!O66) -> 3.4965076 | L55: ='RAW DATA'!M66/'RAW DATA'!E66 -> 0.0085069195
A56: DART | B56: 2024 | C56: ='RAW DATA'!G67/'RAW DATA'!H67 -> 3.3051284 | D56: ='RAW DATA'!G67/'RAW DATA'!E67 -> 0.76771889 | E56: ='RAW DATA'!L67/'RAW DATA'!H67 -> -0.20580365 | F56: ='RAW DATA'!D67/'RAW DATA'!E67 -> 0.97879057 | G56: ='RAW DATA'!C67/'RAW DATA'!F67 -> 0.10048109 | H56: =('RAW DATA'!I67-'RAW DATA'!I66)/'RAW DATA'!I66 -> 0.18088217 | I56: =LN('RAW DATA'!E67) -> 29.45697 | J56: ='RAW DATA'!K67/'RAW DATA'!J67 -> 0.53438262 | K56: =LN('RAW DATA'!O67) -> 3.5263605 | L56: ='RAW DATA'!M67/'RAW DATA'!E67 -> 0.0089020986
A57: DILD | B57: 2020 | C57: ='RAW DATA'!G69/'RAW DATA'!H69 -> 1.5876607 | D57: ='RAW DATA'!G69/'RAW DATA'!E69 -> 0.61355057 | E57: ='RAW DATA'!L69/'RAW DATA'!H69 -> 0.011366589 | F57: ='RAW DATA'!D69/'RAW DATA'!E69 -> 0.71224341 | G57: ='RAW DATA'!C69/'RAW DATA'!F69 -> 1.0343583 | H57: =('RAW DATA'!I69-'RAW DATA'!I68)/'RAW DATA'!I68 -> 0.056643946 | I57: =LN('RAW DATA'!E69) -> 30.384656 | J57: ='RAW DATA'!K69/'RAW DATA'!J69 -> 0.065588874 | K57: =LN('RAW DATA'!O69) -> 3.3672958 | L57: ='RAW DATA'!M69/'RAW DATA'!E69 -> 0.0021840329
A58: DILD | B58: 2021 | C58: ='RAW DATA'!G70/'RAW DATA'!H70 -> 1.7218421 | D58: ='RAW DATA'!G70/'RAW DATA'!E70 -> 0.63260176 | E58: ='RAW DATA'!L70/'RAW DATA'!H70 -> -0.0048062485 | F58: ='RAW DATA'!D70/'RAW DATA'!E70 -> 0.59484712 | G58: ='RAW DATA'!C70/'RAW DATA'!F70 -> 1.027672 | H58: =('RAW DATA'!I70-'RAW DATA'!I69)/'RAW DATA'!I69 -> -0.090875565 | I58: =LN('RAW DATA'!E70) -> 30.431955 | J58: ='RAW DATA'!K70/'RAW DATA'!J70 -> 0.12275341 | K58: =LN('RAW DATA'!O70) -> 3.4011974 | L58: ='RAW DATA'!M70/'RAW DATA'!E70 -> 0.0020832765
A59: DILD | B59: 2022 | C59: ='RAW DATA'!G71/'RAW DATA'!H71 -> 1.6307531 | D59: ='RAW DATA'!G71/'RAW DATA'!E71 -> 0.61988071 | E59: ='RAW DATA'!L71/'RAW DATA'!H71 -> 0.030884591 | F59: ='RAW DATA'!D71/'RAW DATA'!E71 -> 0.60496051 | G59: ='RAW DATA'!C71/'RAW DATA'!F71 -> 1.0433369 | H59: =('RAW DATA'!I71-'RAW DATA'!I70)/'RAW DATA'!I70 -> 0.19786838 | I59: =LN('RAW DATA'!E71) -> 30.425362 | J59: ='RAW DATA'!K71/'RAW DATA'!J71 -> 0.069327781 | K59: =LN('RAW DATA'!O71) -> 3.4339872 | L59: ='RAW DATA'!M71/'RAW DATA'!E71 -> 0.0018130564
A60: DILD | B60: 2023 | C60: ='RAW DATA'!G72/'RAW DATA'!H72 -> 1.233293 | D60: ='RAW DATA'!G72/'RAW DATA'!E72 -> 0.55223072 | E60: ='RAW DATA'!L72/'RAW DATA'!H72 -> 0.11592099 | F60: ='RAW DATA'!D72/'RAW DATA'!E72 -> 0.67578748 | G60: ='RAW DATA'!C72/'RAW DATA'!F72 -> 1.140162 | H60: =('RAW DATA'!I72-'RAW DATA'!I71)/'RAW DATA'!I71 -> 0.24075275 | I60: =LN('RAW DATA'!E72) -> 30.31231 | J60: ='RAW DATA'!K72/'RAW DATA'!J72 -> 0.075458055 | K60: =LN('RAW DATA'!O72) -> 3.4657359 | L60: ='RAW DATA'!M72/'RAW DATA'!E72 -> 0.0022240314
A61: DILD | B61: 2024 | C61: ='RAW DATA'!G73/'RAW DATA'!H73 -> 1.0310851 | D61: ='RAW DATA'!G73/'RAW DATA'!E73 -> 0.50765233 | E61: ='RAW DATA'!L73/'RAW DATA'!H73 -> 0.039107033 | F61: ='RAW DATA'!D73/'RAW DATA'!E73 -> 0.71755009 | G61: ='RAW DATA'!C73/'RAW DATA'!F73 -> 1.0802262 | H61: =('RAW DATA'!I73-'RAW DATA'!I72)/'RAW DATA'!I72 -> -0.3464554 | I61: =LN('RAW DATA'!E73) -> 30.248676 | J61: ='RAW DATA'!K73/'RAW DATA'!J73 -> 0.31533341 | K61: =LN('RAW DATA'!O73) -> 3.4965076 | L61: ='RAW DATA'!M73/'RAW DATA'!E73 -> 0.0026219831
A62: DUTI | B62: 2020 | C62: ='RAW DATA'!G75/'RAW DATA'!H75 -> 0.33139683 | D62: ='RAW DATA'!G75/'RAW DATA'!E75 -> 0.24890913 | E62: ='RAW DATA'!L75/'RAW DATA'!H75 -> 0.061801903 | F62: ='RAW DATA'!D75/'RAW DATA'!E75 -> 0.55838154 | G62: ='RAW DATA'!C75/'RAW DATA'!F75 -> 3.1962557 | H62: =('RAW DATA'!I75-'RAW DATA'!I74)/'RAW DATA'!I74 -> -0.29880932 | I62: =LN('RAW DATA'!E75) -> 30.252324 | J62: ='RAW DATA'!K75/'RAW DATA'!J75 -> 0.15049191 | K62: =LN('RAW DATA'!O75) -> 3.2580965 | L62: ='RAW DATA'!M75/'RAW DATA'!E75 -> 0.0025385032
A63: DUTI | B63: 2021 | C63: ='RAW DATA'!G76/'RAW DATA'!H76 -> 0.3966098 | D63: ='RAW DATA'!G76/'RAW DATA'!E76 -> 0.28398039 | E63: ='RAW DATA'!L76/'RAW DATA'!H76 -> 0.06660711 | F63: ='RAW DATA'!D76/'RAW DATA'!E76 -> 0.48236238 | G63: ='RAW DATA'!C76/'RAW DATA'!F76 -> 3.2667022 | H63: =('RAW DATA'!I76-'RAW DATA'!I75)/'RAW DATA'!I75 -> 0.26263133 | I63: =LN('RAW DATA'!E76) -> 30.359457 | J63: ='RAW DATA'!K76/'RAW DATA'!J76 -> 0.15101852 | K63: =LN('RAW DATA'!O76) -> 3.2958369 | L63: ='RAW DATA'!M76/'RAW DATA'!E76 -> 0.0021824126
A64: DUTI | B64: 2022 | C64: ='RAW DATA'!G77/'RAW DATA'!H77 -> 0.4264905 | D64: ='RAW DATA'!G77/'RAW DATA'!E77 -> 0.29897886 | E64: ='RAW DATA'!L77/'RAW DATA'!H77 -> 0.077492094 | F64: ='RAW DATA'!D77/'RAW DATA'!E77 -> 0.47610889 | G64: ='RAW DATA'!C77/'RAW DATA'!F77 -> 2.4338817 | H64: =('RAW DATA'!I77-'RAW DATA'!I76)/'RAW DATA'!I76 -> 0.38539285 | I64: =LN('RAW DATA'!E77) -> 30.377406 | J64: ='RAW DATA'!K77/'RAW DATA'!J77 -> 0.12667474 | K64: =LN('RAW DATA'!O77) -> 3.3322045 | L64: ='RAW DATA'!M77/'RAW DATA'!E77 -> 0.0020198472
A65: DUTI | B65: 2023 | C65: ='RAW DATA'!G78/'RAW DATA'!H78 -> 0.32027205 | D65: ='RAW DATA'!G78/'RAW DATA'!E78 -> 0.24258034 | E65: ='RAW DATA'!L78/'RAW DATA'!H78 -> 0.11214327 | F65: ='RAW DATA'!D78/'RAW DATA'!E78 -> 0.49556664 | G65: ='RAW DATA'!C78/'RAW DATA'!F78 -> 2.6991048 | H65: =('RAW DATA'!I78-'RAW DATA'!I77)/'RAW DATA'!I77 -> 0.28018384 | I65: =LN('RAW DATA'!E78) -> 30.347799 | J65: ='RAW DATA'!K78/'RAW DATA'!J78 -> 0.137633 | K65: =LN('RAW DATA'!O78) -> 3.3672958 | L65: ='RAW DATA'!M78/'RAW DATA'!E78 -> 0.0014071571
A66: DUTI | B66: 2024 | C66: ='RAW DATA'!G79/'RAW DATA'!H79 -> 0.21020236 | D66: ='RAW DATA'!G79/'RAW DATA'!E79 -> 0.17369191 | E66: ='RAW DATA'!L79/'RAW DATA'!H79 -> 0.11590483 | F66: ='RAW DATA'!D79/'RAW DATA'!E79 -> 0.53369714 | G66: ='RAW DATA'!C79/'RAW DATA'!F79 -> 3.9088185 | H66: =('RAW DATA'!I79-'RAW DATA'!I78)/'RAW DATA'!I78 -> 0.14505359 | I66: =LN('RAW DATA'!E79) -> 30.295635 | J66: ='RAW DATA'!K79/'RAW DATA'!J79 -> 0.11463701 | K66: =LN('RAW DATA'!O79) -> 3.4011974 | L66: ='RAW DATA'!M79/'RAW DATA'!E79 -> 0.0015154966
A67: ELTY | B67: 2020 | C67: ='RAW DATA'!G81/'RAW DATA'!H81 -> 0.40157984 | D67: ='RAW DATA'!G81/'RAW DATA'!E81 -> 0.28651942 | E67: ='RAW DATA'!L81/'RAW DATA'!H81 -> -0.038687298 | F67: ='RAW DATA'!D81/'RAW DATA'!E81 -> 0.77138845 | G67: ='RAW DATA'!C81/'RAW DATA'!F81 -> 1.0892285 | H67: =('RAW DATA'!I81-'RAW DATA'!I80)/'RAW DATA'!I80 -> -0.36963607 | I67: =LN('RAW DATA'!E81) -> 30.101105 | J67: ='RAW DATA'!K81/'RAW DATA'!J81 -> -0.046177312 | K67: =LN('RAW DATA'!O81) -> 3.2188758 | L67: ='RAW DATA'!M81/'RAW DATA'!E81 -> 0.008578217
A68: ELTY | B68: 2021 | C68: ='RAW DATA'!G82/'RAW DATA'!H82 -> 0.43369248 | D68: ='RAW DATA'!G82/'RAW DATA'!E82 -> 0.30250035 | E68: ='RAW DATA'!L82/'RAW DATA'!H82 -> -0.033571582 | F68: ='RAW DATA'!D82/'RAW DATA'!E82 -> 0.76520235 | G68: ='RAW DATA'!C82/'RAW DATA'!F82 -> 1.0287274 | H68: =('RAW DATA'!I82-'RAW DATA'!I81)/'RAW DATA'!I81 -> 0.27295683 | I68: =LN('RAW DATA'!E82) -> 30.089002 | J68: ='RAW DATA'!K82/'RAW DATA'!J82 -> -0.13975786 | K68: =LN('RAW DATA'!O82) -> 3.2580965 | L68: ='RAW DATA'!M82/'RAW DATA'!E82 -> 0.0085899543
A69: ELTY | B69: 2022 | C69: ='RAW DATA'!G83/'RAW DATA'!H83 -> 0.36891307 | D69: ='RAW DATA'!G83/'RAW DATA'!E83 -> 0.26949342 | E69: ='RAW DATA'!L83/'RAW DATA'!H83 -> -0.10903558 | F69: ='RAW DATA'!D83/'RAW DATA'!E83 -> 0.73091673 | G69: ='RAW DATA'!C83/'RAW DATA'!F83 -> 1.2601274 | H69: =('RAW DATA'!I83-'RAW DATA'!I82)/'RAW DATA'!I82 -> 0.30956005 | I69: =LN('RAW DATA'!E83) -> 29.924914 | J69: ='RAW DATA'!K83/'RAW DATA'!J83 -> -0.83203343 | K69: =LN('RAW DATA'!O83) -> 3.2958369 | L69: ='RAW DATA'!M83/'RAW DATA'!E83 -> 0.0095810151
A70: ELTY | B70: 2023 | C70: ='RAW DATA'!G84/'RAW DATA'!H84 -> 0.40902101 | D70: ='RAW DATA'!G84/'RAW DATA'!E84 -> 0.29028737 | E70: ='RAW DATA'!L84/'RAW DATA'!H84 -> -0.18308794 | F70: ='RAW DATA'!D84/'RAW DATA'!E84 -> 0.71859936 | G70: ='RAW DATA'!C84/'RAW DATA'!F84 -> 1.2139958 | H70: =('RAW DATA'!I84-'RAW DATA'!I83)/'RAW DATA'!I83 -> 0.23963233 | I70: =LN('RAW DATA'!E84) -> 29.787314 | J70: ='RAW DATA'!K84/'RAW DATA'!J84 -> -0.11649886 | K70: =LN('RAW DATA'!O84) -> 3.3322045 | L70: ='RAW DATA'!M84/'RAW DATA'!E84 -> 0.007041744
A71: ELTY | B71: 2024 | C71: ='RAW DATA'!G85/'RAW DATA'!H85 -> 0.45114625 | D71: ='RAW DATA'!G85/'RAW DATA'!E85 -> 0.31088958 | E71: ='RAW DATA'!L85/'RAW DATA'!H85 -> -0.016923035 | F71: ='RAW DATA'!D85/'RAW DATA'!E85 -> 0.81454943 | G71: ='RAW DATA'!C85/'RAW DATA'!F85 -> 0.89143313 | H71: =('RAW DATA'!I85-'RAW DATA'!I84)/'RAW DATA'!I84 -> -0.036634495 | I71: =LN('RAW DATA'!E85) -> 29.799162 | J71: ='RAW DATA'!K85/'RAW DATA'!J85 -> 0.33358908 | K71: =LN('RAW DATA'!O85) -> 3.3672958 | L71: ='RAW DATA'!M85/'RAW DATA'!E85 -> 0.0076064826
A72: EMDE | B72: 2020 | C72: ='RAW DATA'!G87/'RAW DATA'!H87 -> 3.4752489 | D72: ='RAW DATA'!G87/'RAW DATA'!E87 -> 0.77654874 | E72: ='RAW DATA'!L87/'RAW DATA'!H87 -> -0.10324882 | F72: ='RAW DATA'!D87/'RAW DATA'!E87 -> 0.24559643 | G72: ='RAW DATA'!C87/'RAW DATA'!F87 -> 2.0854061 | H72: =('RAW DATA'!I87-'RAW DATA'!I86)/'RAW DATA'!I86 -> -0.4812967 | I72: =LN('RAW DATA'!E87) -> 28.528763 | J72: ='RAW DATA'!K87/'RAW DATA'!J87 -> -0.14974084 | K72: =LN('RAW DATA'!O87) -> 2.1972246 | L72: ='RAW DATA'!M87/'RAW DATA'!E87 -> 0.0011303235
A73: EMDE | B73: 2021 | C73: ='RAW DATA'!G88/'RAW DATA'!H88 -> 1.1998507 | D73: ='RAW DATA'!G88/'RAW DATA'!E88 -> 0.5454237 | E73: ='RAW DATA'!L88/'RAW DATA'!H88 -> 0.61016611 | F73: ='RAW DATA'!D88/'RAW DATA'!E88 -> 0.60079065 | G73: ='RAW DATA'!C88/'RAW DATA'!F88 -> 1.4866644 | H73: =('RAW DATA'!I88-'RAW DATA'!I87)/'RAW DATA'!I87 -> 1.0249977 | I73: =LN('RAW DATA'!E88) -> 28.947064 | J73: ='RAW DATA'!K88/'RAW DATA'!J88 -> 1.2682253 | K73: =LN('RAW DATA'!O88) -> 2.3025851 | L73: ='RAW DATA'!M88/'RAW DATA'!E88 -> 0.0006701716
A74: EMDE | B74: 2022 | C74: ='RAW DATA'!G89/'RAW DATA'!H89 -> 1.3020738 | D74: ='RAW DATA'!G89/'RAW DATA'!E89 -> 0.56560907 | E74: ='RAW DATA'!L89/'RAW DATA'!H89 -> -0.041983148 | F74: ='RAW DATA'!D89/'RAW DATA'!E89 -> 0.59862251 | G74: ='RAW DATA'!C89/'RAW DATA'!F89 -> 1.3719755 | H74: =('RAW DATA'!I89-'RAW DATA'!I88)/'RAW DATA'!I88 -> -0.11566496 | I74: =LN('RAW DATA'!E89) -> 28.951109 | J74: ='RAW DATA'!K89/'RAW DATA'!J89 -> 0.43634475 | K74: =LN('RAW DATA'!O89) -> 2.3978953 | L74: ='RAW DATA'!M89/'RAW DATA'!E89 -> 0.00062974408
A75: EMDE | B75: 2023 | C75: ='RAW DATA'!G90/'RAW DATA'!H90 -> 1.5915746 | D75: ='RAW DATA'!G90/'RAW DATA'!E90 -> 0.61413421 | E75: ='RAW DATA'!L90/'RAW DATA'!H90 -> -0.19997978 | F75: ='RAW DATA'!D90/'RAW DATA'!E90 -> 0.57631339 | G75: ='RAW DATA'!C90/'RAW DATA'!F90 -> 1.3448931 | H75: =('RAW DATA'!I90-'RAW DATA'!I89)/'RAW DATA'!I89 -> 0.0074685173 | I75: =LN('RAW DATA'!E90) -> 28.889271 | J75: ='RAW DATA'!K90/'RAW DATA'!J90 -> 0.15603961 | K75: =LN('RAW DATA'!O90) -> 2.4849066 | L75: ='RAW DATA'!M90/'RAW DATA'!E90 -> 0.00053371807
A76: EMDE | B76: 2024 | C76: ='RAW DATA'!G91/'RAW DATA'!H91 -> 0.99357241 | D76: ='RAW DATA'!G91/'RAW DATA'!E91 -> 0.49838792 | E76: ='RAW DATA'!L91/'RAW DATA'!H91 -> 0.27804924 | F76: ='RAW DATA'!D91/'RAW DATA'!E91 -> 0.56821459 | G76: ='RAW DATA'!C91/'RAW DATA'!F91 -> 1.9097523 | H76: =('RAW DATA'!I91-'RAW DATA'!I90)/'RAW DATA'!I90 -> 7.7583508 | I76: =LN('RAW DATA'!E91) -> 28.952182 | J76: ='RAW DATA'!K91/'RAW DATA'!J91 -> 0.066732567 | K76: =LN('RAW DATA'!O91) -> 2.5649494 | L76: ='RAW DATA'!M91/'RAW DATA'!E91 -> 0.00048463899
A77: FMII | B77: 2020 | C77: ='RAW DATA'!G93/'RAW DATA'!H93 -> 0.39272457 | D77: ='RAW DATA'!G93/'RAW DATA'!E93 -> 0.28198294 | E77: ='RAW DATA'!L93/'RAW DATA'!H93 -> -0.0023701084 | F77: ='RAW DATA'!D93/'RAW DATA'!E93 -> 0.69312664 | G77: ='RAW DATA'!C93/'RAW DATA'!F93 -> 3.2730873 | H77: =('RAW DATA'!I93-'RAW DATA'!I92)/'RAW DATA'!I92 -> -0.39085067 | I77: =LN('RAW DATA'!E93) -> 27.492572 | J77: ='RAW DATA'!K93/'RAW DATA'!J93 -> 0.079019153 | K77: =LN('RAW DATA'!O93) -> 2.9957323 | L77: ='RAW DATA'!M93/'RAW DATA'!E93 -> 0.00011045161
A78: FMII | B78: 2021 | C78: ='RAW DATA'!G94/'RAW DATA'!H94 -> 0.36704878 | D78: ='RAW DATA'!G94/'RAW DATA'!E94 -> 0.26849721 | E78: ='RAW DATA'!L94/'RAW DATA'!H94 -> 0.013469151 | F78: ='RAW DATA'!D94/'RAW DATA'!E94 -> 0.71454489 | G78: ='RAW DATA'!C94/'RAW DATA'!F94 -> 1.2799817 | H78: =('RAW DATA'!I94-'RAW DATA'!I93)/'RAW DATA'!I93 -> 0.027619737 | I78: =LN('RAW DATA'!E94) -> 27.490644 | J78: ='RAW DATA'!K94/'RAW DATA'!J94 -> 0.051740866 | K78: =LN('RAW DATA'!O94) -> 3.0445224 | L78: ='RAW DATA'!M94/'RAW DATA'!E94 -> 0.00014395086
A79: FMII | B79: 2022 | C79: ='RAW DATA'!G95/'RAW DATA'!H95 -> 0.15470596 | D79: ='RAW DATA'!G95/'RAW DATA'!E95 -> 0.13397866 | E79: ='RAW DATA'!L95/'RAW DATA'!H95 -> 0.026524387 | F79: ='RAW DATA'!D95/'RAW DATA'!E95 -> 0.74168241 | G79: ='RAW DATA'!C95/'RAW DATA'!F95 -> 2.8458847 | H79: =('RAW DATA'!I95-'RAW DATA'!I94)/'RAW DATA'!I94 -> -0.0069320775 | I79: =LN('RAW DATA'!E95) -> 27.347153 | J79: ='RAW DATA'!K95/'RAW DATA'!J95 -> 0.058273505 | K79: =LN('RAW DATA'!O95) -> 3.0910425 | L79: ='RAW DATA'!M95/'RAW DATA'!E95 -> 9.8745034e-05
A80: FMII | B80: 2023 | C80: ='RAW DATA'!G96/'RAW DATA'!H96 -> 0.16885352 | D80: ='RAW DATA'!G96/'RAW DATA'!E96 -> 0.14446081 | E80: ='RAW DATA'!L96/'RAW DATA'!H96 -> 0.025940957 | F80: ='RAW DATA'!D96/'RAW DATA'!E96 -> 0.76391724 | G80: ='RAW DATA'!C96/'RAW DATA'!F96 -> 2.0603746 | H80: =('RAW DATA'!I96-'RAW DATA'!I95)/'RAW DATA'!I95 -> -0.1869778 | I80: =LN('RAW DATA'!E96) -> 27.385549 | J80: ='RAW DATA'!K96/'RAW DATA'!J96 -> 0.057461655 | K80: =LN('RAW DATA'!O96) -> 3.1354942 | L80: ='RAW DATA'!M96/'RAW DATA'!E96 -> 0.00029712272
A81: FMII | B81: 2024 | C81: ='RAW DATA'!G97/'RAW DATA'!H97 -> 0.14366659 | D81: ='RAW DATA'!G97/'RAW DATA'!E97 -> 0.1256193 | E81: ='RAW DATA'!L97/'RAW DATA'!H97 -> 0.01524888 | F81: ='RAW DATA'!D97/'RAW DATA'!E97 -> 0.77212439 | G81: ='RAW DATA'!C97/'RAW DATA'!F97 -> 2.0987406 | H81: =('RAW DATA'!I97-'RAW DATA'!I96)/'RAW DATA'!I96 -> -0.17055768 | I81: =LN('RAW DATA'!E97) -> 27.379105 | J81: ='RAW DATA'!K97/'RAW DATA'!J97 -> 0.058691703 | K81: =LN('RAW DATA'!O97) -> 3.1780538 | L81: ='RAW DATA'!M97/'RAW DATA'!E97 -> 0.00034459966
A82: GMTD | B82: 2020 | C82: ='RAW DATA'!G99/'RAW DATA'!H99 -> 0.68790843 | D82: ='RAW DATA'!G99/'RAW DATA'!E99 -> 0.4075508 | E82: ='RAW DATA'!L99/'RAW DATA'!H99 -> -0.18113014 | F82: ='RAW DATA'!D99/'RAW DATA'!E99 -> 0.52740345 | G82: ='RAW DATA'!C99/'RAW DATA'!F99 -> 1.3923526 | H82: =('RAW DATA'!I99-'RAW DATA'!I98)/'RAW DATA'!I98 -> -0.18742289 | I82: =LN('RAW DATA'!E99) -> 27.618263 | J82: ='RAW DATA'!K99/'RAW DATA'!J99 -> -0.0046538392 | K82: =LN('RAW DATA'!O99) -> 2.9957323 | L82: ='RAW DATA'!M99/'RAW DATA'!E99 -> 0.00041403821
A83: GMTD | B83: 2021 | C83: ='RAW DATA'!G100/'RAW DATA'!H100 -> 0.92602222 | D83: ='RAW DATA'!G100/'RAW DATA'!E100 -> 0.48079519 | E83: ='RAW DATA'!L100/'RAW DATA'!H100 -> -0.049143251 | F83: ='RAW DATA'!D100/'RAW DATA'!E100 -> 0.54004594 | G83: ='RAW DATA'!C100/'RAW DATA'!F100 -> 1.6995655 | H83: =('RAW DATA'!I100-'RAW DATA'!I99)/'RAW DATA'!I99 -> -0.17336544 | I83: =LN('RAW DATA'!E100) -> 27.701419 | J83: ='RAW DATA'!K100/'RAW DATA'!J100 -> -0.05709234 | K83: =LN('RAW DATA'!O100) -> 3.0445224 | L83: ='RAW DATA'!M100/'RAW DATA'!E100 -> 0.0011258602
A84: GMTD | B84: 2022 | C84: ='RAW DATA'!G101/'RAW DATA'!H101 -> 1.0495508 | D84: ='RAW DATA'!G101/'RAW DATA'!E101 -> 0.51208821 | E84: ='RAW DATA'!L101/'RAW DATA'!H101 -> 0.015885714 | F84: ='RAW DATA'!D101/'RAW DATA'!E101 -> 0.57118312 | G84: ='RAW DATA'!C101/'RAW DATA'!F101 -> 1.3566499 | H84: =('RAW DATA'!I101-'RAW DATA'!I100)/'RAW DATA'!I100 -> 1.2728674 | I84: =LN('RAW DATA'!E101) -> 27.780252 | J84: ='RAW DATA'!K101/'RAW DATA'!J101 -> 0.0059855459 | K84: =LN('RAW DATA'!O101) -> 3.0910425 | L84: ='RAW DATA'!M101/'RAW DATA'!E101 -> 0.0021094494
A85: GMTD | B85: 2023 | C85: ='RAW DATA'!G102/'RAW DATA'!H102 -> 0.72908647 | D85: ='RAW DATA'!G102/'RAW DATA'!E102 -> 0.42165992 | E85: ='RAW DATA'!L102/'RAW DATA'!H102 -> 0.18528975 | F85: ='RAW DATA'!D102/'RAW DATA'!E102 -> 0.51791805 | G85: ='RAW DATA'!C102/'RAW DATA'!F102 -> 1.8467209 | H85: =('RAW DATA'!I102-'RAW DATA'!I101)/'RAW DATA'!I101 -> 0.20429357 | I85: =LN('RAW DATA'!E102) -> 27.816617 | J85: ='RAW DATA'!K102/'RAW DATA'!J102 -> 0.0032386071 | K85: =LN('RAW DATA'!O102) -> 3.1354942 | L85: ='RAW DATA'!M102/'RAW DATA'!E102 -> 0.0022130542
A86: GMTD | B86: 2024 | C86: ='RAW DATA'!G103/'RAW DATA'!H103 -> 0.55746679 | D86: ='RAW DATA'!G103/'RAW DATA'!E103 -> 0.35793174 | E86: ='RAW DATA'!L103/'RAW DATA'!H103 -> 0.16470795 | F86: ='RAW DATA'!D103/'RAW DATA'!E103 -> 0.44859735 | G86: ='RAW DATA'!C103/'RAW DATA'!F103 -> 3.1813442 | H86: =('RAW DATA'!I103-'RAW DATA'!I102)/'RAW DATA'!I102 -> 0.054283478 | I86: =LN('RAW DATA'!E103) -> 27.888823 | J86: ='RAW DATA'!K103/'RAW DATA'!J103 -> 0.0028097611 | K86: =LN('RAW DATA'!O103) -> 3.1780538 | L86: ='RAW DATA'!M103/'RAW DATA'!E103 -> 0.0045933865
A87: GPRA | B87: 2020 | C87: ='RAW DATA'!G105/'RAW DATA'!H105 -> 0.64003347 | D87: ='RAW DATA'!G105/'RAW DATA'!E105 -> 0.39025635 | E87: ='RAW DATA'!L105/'RAW DATA'!H105 -> 0.032995489 | F87: ='RAW DATA'!D105/'RAW DATA'!E105 -> 0.15836628 | G87: ='RAW DATA'!C105/'RAW DATA'!F105 -> 3.5522725 | H87: =('RAW DATA'!I105-'RAW DATA'!I104)/'RAW DATA'!I104 -> -0.18582421 | I87: =LN('RAW DATA'!E105) -> 28.177616 | J87: ='RAW DATA'!K105/'RAW DATA'!J105 -> 0.011304825 | K87: =LN('RAW DATA'!O105) -> 2.5649494 | L87: ='RAW DATA'!M105/'RAW DATA'!E105 -> 0.0025858647
A88: GPRA | B88: 2021 | C88: ='RAW DATA'!G106/'RAW DATA'!H106 -> 0.59194404 | D88: ='RAW DATA'!G106/'RAW DATA'!E106 -> 0.37183722 | E88: ='RAW DATA'!L106/'RAW DATA'!H106 -> 0.044793249 | F88: ='RAW DATA'!D106/'RAW DATA'!E106 -> 0.21669806 | G88: ='RAW DATA'!C106/'RAW DATA'!F106 -> 2.9715584 | H88: =('RAW DATA'!I106-'RAW DATA'!I105)/'RAW DATA'!I105 -> 0.37971961 | I88: =LN('RAW DATA'!E106) -> 28.196648 | J88: ='RAW DATA'!K106/'RAW DATA'!J106 -> 0.15813061 | K88: =LN('RAW DATA'!O106) -> 2.6390573 | L88: ='RAW DATA'!M106/'RAW DATA'!E106 -> 0.0025270455
A89: GPRA | B89: 2022 | C89: ='RAW DATA'!G107/'RAW DATA'!H107 -> 0.51154705 | D89: ='RAW DATA'!G107/'RAW DATA'!E107 -> 0.33842615 | E89: ='RAW DATA'!L107/'RAW DATA'!H107 -> 0.06479113 | F89: ='RAW DATA'!D107/'RAW DATA'!E107 -> 0.20596379 | G89: ='RAW DATA'!C107/'RAW DATA'!F107 -> 2.9558883 | H89: =('RAW DATA'!I107-'RAW DATA'!I106)/'RAW DATA'!I106 -> -0.17095225 | I89: =LN('RAW DATA'!E107) -> 28.208396 | J89: ='RAW DATA'!K107/'RAW DATA'!J107 -> 0.11292738 | K89: =LN('RAW DATA'!O107) -> 2.7080502 | L89: ='RAW DATA'!M107/'RAW DATA'!E107 -> 0.002620645
A90: GPRA | B90: 2023 | C90: ='RAW DATA'!G108/'RAW DATA'!H108 -> 0.5407557 | D90: ='RAW DATA'!G108/'RAW DATA'!E108 -> 0.35096784 | E90: ='RAW DATA'!L108/'RAW DATA'!H108 -> 0.076065669 | F90: ='RAW DATA'!D108/'RAW DATA'!E108 -> 0.21161752 | G90: ='RAW DATA'!C108/'RAW DATA'!F108 -> 3.5535767 | H90: =('RAW DATA'!I108-'RAW DATA'!I107)/'RAW DATA'!I107 -> 0.24071106 | I90: =LN('RAW DATA'!E108) -> 28.301018 | J90: ='RAW DATA'!K108/'RAW DATA'!J108 -> 0.1137553 | K90: =LN('RAW DATA'!O108) -> 2.7725887 | L90: ='RAW DATA'!M108/'RAW DATA'!E108 -> 0.0025828712
A91: GPRA | B91: 2024 | C91: ='RAW DATA'!G109/'RAW DATA'!H109 -> 0.44218273 | D91: ='RAW DATA'!G109/'RAW DATA'!E109 -> 0.30660659 | E91: ='RAW DATA'!L109/'RAW DATA'!H109 -> 0.090564372 | F91: ='RAW DATA'!D109/'RAW DATA'!E109 -> 0.2265956 | G91: ='RAW DATA'!C109/'RAW DATA'!F109 -> 4.2585353 | H91: =('RAW DATA'!I109-'RAW DATA'!I108)/'RAW DATA'!I108 -> 0.125201 | I91: =LN('RAW DATA'!E109) -> 28.310422 | J91: ='RAW DATA'!K109/'RAW DATA'!J109 -> 0.09880209 | K91: =LN('RAW DATA'!O109) -> 2.8332133 | L91: ='RAW DATA'!M109/'RAW DATA'!E109 -> 0.0026050249
A92: INPP | B92: 2020 | C92: ='RAW DATA'!G111/'RAW DATA'!H111 -> 0.32658546 | D92: ='RAW DATA'!G111/'RAW DATA'!E111 -> 0.24618502 | E92: ='RAW DATA'!L111/'RAW DATA'!H111 -> -0.08377185 | F92: ='RAW DATA'!D111/'RAW DATA'!E111 -> 0.90128409 | G92: ='RAW DATA'!C111/'RAW DATA'!F111 -> 3.7113693 | H92: =('RAW DATA'!I111-'RAW DATA'!I110)/'RAW DATA'!I110 -> -0.55893609 | I92: =LN('RAW DATA'!E111) -> 29.666655 | J92: ='RAW DATA'!K111/'RAW DATA'!J111 -> 0.038399501 | K92: =LN('RAW DATA'!O111) -> 2.7725887 | L92: ='RAW DATA'!M111/'RAW DATA'!E111 -> 0.0082623829
A93: INPP | B93: 2021 | C93: ='RAW DATA'!G112/'RAW DATA'!H112 -> 0.57479708 | D93: ='RAW DATA'!G112/'RAW DATA'!E112 -> 0.36499755 | E93: ='RAW DATA'!L112/'RAW DATA'!H112 -> -0.0073826261 | F93: ='RAW DATA'!D112/'RAW DATA'!E112 -> 0.79386464 | G93: ='RAW DATA'!C112/'RAW DATA'!F112 -> 2.461102 | H93: =('RAW DATA'!I112-'RAW DATA'!I111)/'RAW DATA'!I111 -> 0.077137665 | I93: =LN('RAW DATA'!E112) -> 29.825007 | J93: ='RAW DATA'!K112/'RAW DATA'!J112 -> 0.004375349 | K93: =LN('RAW DATA'!O112) -> 2.8332133 | L93: ='RAW DATA'!M112/'RAW DATA'!E112 -> 0.0063928578
A94: INPP | B94: 2022 | C94: ='RAW DATA'!G113/'RAW DATA'!H113 -> 0.59651513 | D94: ='RAW DATA'!G113/'RAW DATA'!E113 -> 0.37363575 | E94: ='RAW DATA'!L113/'RAW DATA'!H113 -> 0.012106891 | F94: ='RAW DATA'!D113/'RAW DATA'!E113 -> 0.77330908 | G94: ='RAW DATA'!C113/'RAW DATA'!F113 -> 3.1330315 | H94: =('RAW DATA'!I113-'RAW DATA'!I112)/'RAW DATA'!I112 -> 1.2342585 | I94: =LN('RAW DATA'!E113) -> 29.846284 | J94: ='RAW DATA'!K113/'RAW DATA'!J113 -> 0.20663658 | K94: =LN('RAW DATA'!O113) -> 2.8903718 | L94: ='RAW DATA'!M113/'RAW DATA'!E113 -> 0.0065581827
A95: INPP | B95: 2023 | C95: ='RAW DATA'!G114/'RAW DATA'!H114 -> 0.57637075 | D95: ='RAW DATA'!G114/'RAW DATA'!E114 -> 0.36563147 | E95: ='RAW DATA'!L114/'RAW DATA'!H114 -> 0.031188677 | F95: ='RAW DATA'!D114/'RAW DATA'!E114 -> 0.78414835 | G95: ='RAW DATA'!C114/'RAW DATA'!F114 -> 1.9149747 | H95: =('RAW DATA'!I114-'RAW DATA'!I113)/'RAW DATA'!I113 -> 0.1561102 | I95: =LN('RAW DATA'!E114) -> 29.865889 | J95: ='RAW DATA'!K114/'RAW DATA'!J114 -> 0.17313995 | K95: =LN('RAW DATA'!O114) -> 2.944439 | L95: ='RAW DATA'!M114/'RAW DATA'!E114 -> 0.0067210154
A96: INPP | B96: 2024 | C96: ='RAW DATA'!G115/'RAW DATA'!H115 -> 0.54319832 | D96: ='RAW DATA'!G115/'RAW DATA'!E115 -> 0.35199515 | E96: ='RAW DATA'!L115/'RAW DATA'!H115 -> 0.066409669 | F96: ='RAW DATA'!D115/'RAW DATA'!E115 -> 0.84439079 | G96: ='RAW DATA'!C115/'RAW DATA'!F115 -> 1.9418532 | H96: =('RAW DATA'!I115-'RAW DATA'!I114)/'RAW DATA'!I114 -> 0.18552452 | I96: =LN('RAW DATA'!E115) -> 29.904683 | J96: ='RAW DATA'!K115/'RAW DATA'!J115 -> 0.16556855 | K96: =LN('RAW DATA'!O115) -> 2.9957323 | L96: ='RAW DATA'!M115/'RAW DATA'!E115 -> 0.0079122725
A97: JRPT | B97: 2020 | C97: ='RAW DATA'!G117/'RAW DATA'!H117 -> 0.45795533 | D97: ='RAW DATA'!G117/'RAW DATA'!E117 -> 0.31410793 | E97: ='RAW DATA'!L117/'RAW DATA'!H117 -> 0.12868664 | F97: ='RAW DATA'!D117/'RAW DATA'!E117 -> 0.64861456 | G97: ='RAW DATA'!C117/'RAW DATA'!F117 -> 1.2433515 | H97: =('RAW DATA'!I117-'RAW DATA'!I116)/'RAW DATA'!I116 -> -0.098349643 | I97: =LN('RAW DATA'!E117) -> 30.07176 | J97: ='RAW DATA'!K117/'RAW DATA'!J117 -> 0.010739966 | K97: =LN('RAW DATA'!O117) -> 3.2580965 | L97: ='RAW DATA'!M117/'RAW DATA'!E117 -> 0.0008432913
A98: JRPT | B98: 2021 | C98: ='RAW DATA'!G118/'RAW DATA'!H118 -> 0.44081994 | D98: ='RAW DATA'!G118/'RAW DATA'!E118 -> 0.30595075 | E98: ='RAW DATA'!L118/'RAW DATA'!H118 -> 0.096485929 | F98: ='RAW DATA'!D118/'RAW DATA'!E118 -> 0.71289398 | G98: ='RAW DATA'!C118/'RAW DATA'!F118 -> 1.0273376 | H98: =('RAW DATA'!I118-'RAW DATA'!I117)/'RAW DATA'!I117 -> -0.0048509004 | I98: =LN('RAW DATA'!E118) -> 30.094717 | J98: ='RAW DATA'!K118/'RAW DATA'!J118 -> 0.087127089 | K98: =LN('RAW DATA'!O118) -> 3.2958369 | L98: ='RAW DATA'!M118/'RAW DATA'!E118 -> 0.00091221452
A99: JRPT | B99: 2022 | C99: ='RAW DATA'!G119/'RAW DATA'!H119 -> 0.41933917 | D99: ='RAW DATA'!G119/'RAW DATA'!E119 -> 0.29544677 | E99: ='RAW DATA'!L119/'RAW DATA'!H119 -> 0.1019194 | F99: ='RAW DATA'!D119/'RAW DATA'!E119 -> 0.7208192 | G99: ='RAW DATA'!C119/'RAW DATA'!F119 -> 1.0089427 | H99: =('RAW DATA'!I119-'RAW DATA'!I118)/'RAW DATA'!I118 -> 0.038922745 | I99: =LN('RAW DATA'!E119) -> 30.136694 | J99: ='RAW DATA'!K119/'RAW DATA'!J119 -> 0.083756005 | K99: =LN('RAW DATA'!O119) -> 3.3322045 | L99: ='RAW DATA'!M119/'RAW DATA'!E119 -> 0.00086311967
A100: JRPT | B100: 2023 | C100: ='RAW DATA'!G120/'RAW DATA'!H120 -> 0.42456406 | D100: ='RAW DATA'!G120/'RAW DATA'!E120 -> 0.29803087 | E100: ='RAW DATA'!L120/'RAW DATA'!H120 -> 0.11049032 | F100: ='RAW DATA'!D120/'RAW DATA'!E120 -> 0.75523101 | G100: ='RAW DATA'!C120/'RAW DATA'!F120 -> 0.87471681 | H100: =('RAW DATA'!I120-'RAW DATA'!I119)/'RAW DATA'!I119 -> 0.10831062 | I100: =LN('RAW DATA'!E120) -> 30.21176 | J100: ='RAW DATA'!K120/'RAW DATA'!J120 -> 0.084564628 | K100: =LN('RAW DATA'!O120) -> 3.3672958 | L100: ='RAW DATA'!M120/'RAW DATA'!E120 -> 0.00093185778
...
